Workbook

Sheet Version History
A5: Date | B5: Version | C5: Description | D5: Prepared by | E5: Reviewed & approved by
A6: 45660 | B6: 1 | C6: Size base Estimation Model First baseline | D6: SEPG Team | E6: SEPG Head
A7: 46174 | B7: 1.4 | C7: Cycle 4 (Jan-May 2026) Size based Estimation - All modules updated | D7: SEPG Team | E7: SEPG Head
A8: 46190 | B8: 2.0 | C8: Cycle 4 Estimation corrected – All module Size and Effort values updated per CMMI L5 size-based estimation guidelines. Productivity=0.18 pt/hr; VAF=1.01; Risk=5%; PM=10%. Sizes: ANS=26, AST=9, BHR=23, CUBE=69, DHR=89, FHTC=53, MST=38, MAT=51, NRM=22, O&M=96, SAH=10, SVS=11. All hardcoded Size/TotalCount cells converted to Excel formulas. Complexity distributions recalibrated per Guidelines sheet. | D8: SEPG Team | E8: SEPG Head
A9: 46314 | B9: 3.0 | C9: Cycle 5 (Jun-Sep 2026) Size based Estimation - all modules. Productivity=0.19 pt/hr (1 point = ~5.26 hrs, revised from 0.179); VAF=1.01; Risk=5%; PM=10%. Sources: Jun-Sep MoMs, PSRs, Sprint 17-20 user stories, timesheet. Total size=475. Sizes: O&M=136, SAH=30, DHR=46, MST=22, FHTC=15, CUBE=9, MAT=10, NRM=16, SVS=20, SVS-GP=27, ANS=6, AST=7, BHR=5, AI=15, CMMI=15, ESIGN=21, BISAC/BISAG=21, OTH=54. | D9: SEPG Team | E9: SEPG Head

Sheet Master
A1: Estimation Elements
A2: New Development | B2: Enhancement and customization
A3: Web Page / Screen with no of input fields | B3: Web Page / Screen with no of input fields
A4: Type of exit scenario | B4: Type of exit scenario
A5: No of Validation on the fields | B5: No of Validation on the fields
A6: No of Prefilled fields | B6: No of Prefilled fields
A7: No of API Integrations | B7: No of API Integrations
A8: No API integrations for saving the data | B8: No API integrations for saving the data
A9: Queries or Business rules for the application | B9: Queries or Business rules for the application
A10: No of Integration | B10: No of Integration
A11: mobile App-UI | B11: mobile App-UI
A12: Data Migration | B12: Data Migration
A13: Reports | B13: Reports
A25: Complexity | B25: Type of work | C25: VAF Rating
A26: Low | B26: New Development | C26: 5 | D26: 5 - Very Strong Influence
A27: Medium | B27: Enhancement and customization | C27: 4 | D27: 4 - Strong Influence
A28: High | C28: 3 | D28: 3 - Average Influence
A29: Complex | C29: 2 | D29: 2 - Moderate Influence
C30: 1 | D30: 1- Slight Influence
C31: 0 | D31: 0 - No Influence
A37: Effort Distribution Guidelines
B38: Effort Distribution | C38: Cost
C39: Min | D39: Max
A40: Business Analyst | B40: 0.15 | C40: 4000 | D40: 6000
A41: Solution Architecht | B41: 0.1 | C41: 6000 | D41: 8000
A42: Developer / Data Scientist | B42: 0.4 | C42: 3000 | D42: 5000
A43: Tester | B43: 0.2 | C43: 2500 | D43: 5000
A44: Project Manager | B44: 0.1 | C44: 8000 | D44: 10000
A45: Infrastructure Setup | B45: 0.05 | C45: 3000 | D45: 5000
A46: Business Analyst | B46: 0.15
A47: Solution Architecht | B47: 0.1
A48: Developer / Data Scientist | B48: 0.4
A49: Tester | B49: 0.2
A50: Project Manager | B50: 0.1
A51: Infrastructure Setup | B51: 0.05

Sheet Baseline Productivity 
A3: Type of work | B3: Calculated Productivity | C3: Targated Productivity | D3: Unit
A4: Development & Enhancement | C4: 0.19 | D4: Point / per hour
C9: 1 Point | D9: =1/C4 -> 5.2631579
D10: ~5.26 hours
A12: Revision note (Cycle 5, Jun-Sep 2026)
A13: Targeted productivity increased from 0.179 to 0.19 pt/hr: 1 story point = ~5.26 hours (was ~5.6 hours). All module sheets read the value in C4.
A14: Complexity weights unchanged (Low = 1, Medium = 3, High = 5). VAF ratings, 5% risk contingency and 10% project management carried forward from Cycle 4 V2.0.

Sheet Guidelines
B2: Complexity | C2: 1 | D2: 3 | E2: 5
A3: Work Type | B3: Component | C3: Low | D3: Medium | E3: High
A4: Development | B4: Web Page / Screen with no of input fields | C4: 10 | D4: 10-15 | E4: > 15 | F4: Elements Label Graph Tile Grid Pop-up Drop Down Data Entery Field Button Custom Built element | K4: 1
B5: Type of exit scenario | C5: 1 | D5: 1 to 2 | E5: >3 | H5: label | I5: text box
B6: No of Validation on the fields | C6: 1 to 5 | D6: 5 To 10 | E6: >10 | H6: button
B7: No of Prefilled fields | C7: 10 to 30 | D7: 30 to 50 | E7: >50 | H7: drop down
B8: No of API Integrations | C8: 2 | D8: 2 to 5 | E8: > 5 | H8: checkbox
B9: No API integrations for saving the data | C9: 3 | D9: 3 to 5 | E9: >5 | H9: aadhar
B10: Queries or Business rules for the application | C10: No validation or business rules. One data store | D10: No validation or business rules. Up to 3 data stores | E10: Validation or business rules involved. Multiple data stores | H10: samagra integration
B11: No of Integration | C11: 2 | D11: 2 to 5 | E11: >5 | H11: report
B12: mobile App-UI | C12: Static screen | D12: Screen with 2-4 internal components | E12: Screen with external components | H12: MObile app
B13: Data Migration | C13: Master Table | D13: Table with data errors and involves Data validation and cleansing | E13: Table with relationship with data errors and requires data validation and cleansing | H13: submit
B14: Reports | C14: tabular report. <10 columns. 1 data source Elements( Table, PIE chart, Report count: 1-2 | D14: 2-3 data source. Simple (Pie/Bar) chart Elements( Stack,Line etc.) Report type: 3-5 | E14: >3 data source. Multiple complex graphs Elements( Doughnut, Trend analysis etc.) Report type: More than 5 | H14: clear
H15: reset
F19: Code element Data Tranformation Data Pre-processing Custom Build element API creation for UI\UX API Integration

Sheet Summary
A1: Jal Rekha - Cycle 5 (Jun-Sep 2026) Size Based Estimation Summary
A2: All figures link to the module estimation sheets. Productivity is read from Baseline Productivity!C4.
A4: Estimation Sheet | B4: Stories | C4: Low | D4: Medium | E4: High | F4: Size (Points) | G4: Productivity (pt/hr) | H4: Effort (Man hours) | I4: VAF | J4: Total Planned Effort (Man hours) | K4: Range Low (-5%) | L4: Range High (+5%) | M4: Check vs Story Mapping
A5: O&M Estimation | B5: =C5+D5+E5 -> 46 | C5: =SUM('O&M Estimation'!D8:D15) -> 11 | D5: =SUM('O&M Estimation'!E8:E15) -> 25 | E5: =SUM('O&M Estimation'!F8:F15) -> 10 | F5: ='O&M Estimation'!G16 -> 136 | G5: ='O&M Estimation'!C20 -> 0.19 | H5: ='O&M Estimation'!C22 -> 715.78947 | I5: ='O&M Estimation'!C23 -> 1.01 | J5: ='O&M Estimation'!C26 -> 831.38947 | K5: ='O&M Estimation'!D28 -> 789.82 | L5: ='O&M Estimation'!C28 -> 872.95895 | M5: =IF(AND(COUNTIFS('Story Mapping'!$H$9:$H$196,A5,'Story Mapping'!$L$9:$L$196,"Low")=C5,COUNTIFS('Story Mapping'!$H$9:$H$196,A5,'Story Mapping'!$L$9:$L$196,"Medium")=D5,COUNTIFS('Story Mapping'!$H$9:$H$196,A5,'Story Mapping'!$L$9:$L$196,"High")=E5),"OK","MISMATCH") -> OK
A6: Sahbhagita Estimation | B6: =C6+D6+E6 -> 12 | C6: =SUM('Sahbhagita Estimation'!D8:D11) -> 4 | D6: =SUM('Sahbhagita Estimation'!E8:E11) -> 7 | E6: =SUM('Sahbhagita Estimation'!F8:F11) -> 1 | F6: ='Sahbhagita Estimation'!G12 -> 30 | G6: ='Sahbhagita Estimation'!C16 -> 0.19 | H6: ='Sahbhagita Estimation'!C18 -> 157.89474 | I6: ='Sahbhagita Estimation'!C19 -> 1.01 | J6: ='Sahbhagita Estimation'!C22 -> 183.39474 | K6: ='Sahbhagita Estimation'!D24 -> 174.225 | L6: ='Sahbhagita Estimation'!C24 -> 192.56447 | M6: =IF(AND(COUNTIFS('Story Mapping'!$H$9:$H$196,A6,'Story Mapping'!$L$9:$L$196,"Low")=C6,COUNTIFS('Story Mapping'!$H$9:$H$196,A6,'Story Mapping'!$L$9:$L$196,"Medium")=D6,COUNTIFS('Story Mapping'!$H$9:$H$196,A6,'Story Mapping'!$L$9:$L$196,"High")=E6),"OK","MISMATCH") -> OK
A7: Dhara Estimation | B7: =C7+D7+E7 -> 14 | C7: =SUM('Dhara Estimation'!D8:D12) -> 1 | D7: =SUM('Dhara Estimation'!E8:E12) -> 10 | E7: =SUM('Dhara Estimation'!F8:F12) -> 3 | F7: ='Dhara Estimation'!G13 -> 46 | G7: ='Dhara Estimation'!C17 -> 0.19 | H7: ='Dhara Estimation'!C19 -> 242.10526 | I7: ='Dhara Estimation'!C20 -> 1.01 | J7: ='Dhara Estimation'!C23 -> 281.20526 | K7: ='Dhara Estimation'!D25 -> 267.145 | L7: ='Dhara Estimation'!C25 -> 295.26553 | M7: =IF(AND(COUNTIFS('Story Mapping'!$H$9:$H$196,A7,'Story Mapping'!$L$9:$L$196,"Low")=C7,COUNTIFS('Story Mapping'!$H$9:$H$196,A7,'Story Mapping'!$L$9:$L$196,"Medium")=D7,COUNTIFS('Story Mapping'!$H$9:$H$196,A7,'Story Mapping'!$L$9:$L$196,"High")=E7),"OK","MISMATCH") -> OK
A8: Master Estimation | B8: =C8+D8+E8 -> 10 | C8: =SUM('Master Estimation'!D8:D10) -> 4 | D8: =SUM('Master Estimation'!E8:E10) -> 6 | E8: =SUM('Master Estimation'!F8:F10) -> 0 | F8: ='Master Estimation'!G11 -> 22 | G8: ='Master Estimation'!C15 -> 0.19 | H8: ='Master Estimation'!C17 -> 115.78947 | I8: ='Master Estimation'!C18 -> 1.01 | J8: ='Master Estimation'!C21 -> 134.48947 | K8: ='Master Estimation'!D23 -> 127.765 | L8: ='Master Estimation'!C23 -> 141.21395 | M8: =IF(AND(COUNTIFS('Story Mapping'!$H$9:$H$196,A8,'Story Mapping'!$L$9:$L$196,"Low")=C8,COUNTIFS('Story Mapping'!$H$9:$H$196,A8,'Story Mapping'!$L$9:$L$196,"Medium")=D8,COUNTIFS('Story Mapping'!$H$9:$H$196,A8,'Story Mapping'!$L$9:$L$196,"High")=E8),"OK","MISMATCH") -> OK
A9: FHTC Estimation | B9: =C9+D9+E9 -> 7 | C9: =SUM('FHTC Estimation'!D8:D10) -> 4 | D9: =SUM('FHTC Estimation'!E8:E10) -> 2 | E9: =SUM('FHTC Estimation'!F8:F10) -> 1 | F9: ='FHTC Estimation'!G11 -> 15 | G9: ='FHTC Estimation'!C15 -> 0.19 | H9: ='FHTC Estimation'!C17 -> 78.947368 | I9: ='FHTC Estimation'!C18 -> 1.01 | J9: ='FHTC Estimation'!C21 -> 91.697368 | K9: ='FHTC Estimation'!D23 -> 87.1125 | L9: ='FHTC Estimation'!C23 -> 96.282237 | M9: =IF(AND(COUNTIFS('Story Mapping'!$H$9:$H$196,A9,'Story Mapping'!$L$9:$L$196,"Low")=C9,COUNTIFS('Story Mapping'!$H$9:$H$196,A9,'Story Mapping'!$L$9:$L$196,"Medium")=D9,COUNTIFS('Story Mapping'!$H$9:$H$196,A9,'Story Mapping'!$L$9:$L$196,"High")=E9),"OK","MISMATCH") -> OK
A10: Cube Testing Estimation | B10: =C10+D10+E10 -> 7 | C10: =SUM('Cube Testing Estimation'!D8:D10) -> 6 | D10: =SUM('Cube Testing Estimation'!E8:E10) -> 1 | E10: =SUM('Cube Testing Estimation'!F8:F10) -> 0 | F10: ='Cube Testing Estimation'!G11 -> 9 | G10: ='Cube Testing Estimation'!C15 -> 0.19 | H10: ='Cube Testing Estimation'!C17 -> 47.368421 | I10: ='Cube Testing Estimation'!C18 -> 1.01 | J10: ='Cube Testing Estimation'!C21 -> 55.018421 | K10: ='Cube Testing Estimation'!D23 -> 52.2675 | L10: ='Cube Testing Estimation'!C23 -> 57.769342 | M10: =IF(AND(COUNTIFS('Story Mapping'!$H$9:$H$196,A10,'Story Mapping'!$L$9:$L$196,"Low")=C10,COUNTIFS('Story Mapping'!$H$9:$H$196,A10,'Story Mapping'!$L$9:$L$196,"Medium")=D10,COUNTIFS('Story Mapping'!$H$9:$H$196,A10,'Story Mapping'!$L$9:$L$196,"High")=E10),"OK","MISMATCH") -> OK
A11: Material Testing Estimation | B11: =C11+D11+E11 -> 4 | C11: =SUM('Material Testing Estimation'!D8:D10) -> 2 | D11: =SUM('Material Testing Estimation'!E8:E10) -> 1 | E11: =SUM('Material Testing Estimation'!F8:F10) -> 1 | F11: ='Material Testing Estimation'!G11 -> 10 | G11: ='Material Testing Estimation'!C15 -> 0.19 | H11: ='Material Testing Estimation'!C17 -> 52.631579 | I11: ='Material Testing Estimation'!C18 -> 1.01 | J11: ='Material Testing Estimation'!C21 -> 61.131579 | K11: ='Material Testing Estimation'!D23 -> 58.075 | L11: ='Material Testing Estimation'!C23 -> 64.188158 | M11: =IF(AND(COUNTIFS('Story Mapping'!$H$9:$H$196,A11,'Story Mapping'!$L$9:$L$196,"Low")=C11,COUNTIFS('Story Mapping'!$H$9:$H$196,A11,'Story Mapping'!$L$9:$L$196,"Medium")=D11,COUNTIFS('Story Mapping'!$H$9:$H$196,A11,'Story Mapping'!$L$9:$L$196,"High")=E11),"OK","MISMATCH") -> OK
A12: Nirmal Estimation | B12: =C12+D12+E12 -> 6 | C12: =SUM('Nirmal Estimation'!D8:D9) -> 2 | D12: =SUM('Nirmal Estimation'!E8:E9) -> 3 | E12: =SUM('Nirmal Estimation'!F8:F9) -> 1 | F12: ='Nirmal Estimation'!G10 -> 16 | G12: ='Nirmal Estimation'!C14 -> 0.19 | H12: ='Nirmal Estimation'!C16 -> 84.210526 | I12: ='Nirmal Estimation'!C17 -> 1.01 | J12: ='Nirmal Estimation'!C20 -> 97.810526 | K12: ='Nirmal Estimation'!D22 -> 92.92 | L12: ='Nirmal Estimation'!C22 -> 102.70105 | M12: =IF(AND(COUNTIFS('Story Mapping'!$H$9:$H$196,A12,'Story Mapping'!$L$9:$L$196,"Low")=C12,COUNTIFS('Story Mapping'!$H$9:$H$196,A12,'Story Mapping'!$L$9:$L$196,"Medium")=D12,COUNTIFS('Story Mapping'!$H$9:$H$196,A12,'Story Mapping'!$L$9:$L$196,"High")=E12),"OK","MISMATCH") -> OK
A13: SVS Estimation | B13: =C13+D13+E13 -> 8 | C13: =SUM('SVS Estimation'!D8:D11) -> 4 | D13: =SUM('SVS Estimation'!E8:E11) -> 2 | E13: =SUM('SVS Estimation'!F8:F11) -> 2 | F13: ='SVS Estimation'!G12 -> 20 | G13: ='SVS Estimation'!C16 -> 0.19 | H13: ='SVS Estimation'!C18 -> 105.26316 | I13: ='SVS Estimation'!C19 -> 1.01 | J13: ='SVS Estimation'!C22 -> 122.26316 | K13: ='SVS Estimation'!D24 -> 116.15 | L13: ='SVS Estimation'!C24 -> 128.37632 | M13: =IF(AND(COUNTIFS('Story Mapping'!$H$9:$H$196,A13,'Story Mapping'!$L$9:$L$196,"Low")=C13,COUNTIFS('Story Mapping'!$H$9:$H$196,A13,'Story Mapping'!$L$9:$L$196,"Medium")=D13,COUNTIFS('Story Mapping'!$H$9:$H$196,A13,'Story Mapping'!$L$9:$L$196,"High")=E13),"OK","MISMATCH") -> OK
A14: SVS Anusharavan GP Estimation | B14: =C14+D14+E14 -> 7 | C14: =SUM('SVS Anusharavan GP Estimation'!D8:D10) -> 0 | D14: =SUM('SVS Anusharavan GP Estimation'!E8:E10) -> 4 | E14: =SUM('SVS Anusharavan GP Estimation'!F8:F10) -> 3 | F14: ='SVS Anusharavan GP Estimation'!G11 -> 27 | G14: ='SVS Anusharavan GP Estimation'!C15 -> 0.19 | H14: ='SVS Anusharavan GP Estimation'!C17 -> 142.10526 | I14: ='SVS Anusharavan GP Estimation'!C18 -> 1.01 | J14: ='SVS Anusharavan GP Estimation'!C21 -> 165.05526 | K14: ='SVS Anusharavan GP Estimation'!D23 -> 156.8025 | L14: ='SVS Anusharavan GP Estimation'!C23 -> 173.30803 | M14: =IF(AND(COUNTIFS('Story Mapping'!$H$9:$H$196,A14,'Story Mapping'!$L$9:$L$196,"Low")=C14,COUNTIFS('Story Mapping'!$H$9:$H$196,A14,'Story Mapping'!$L$9:$L$196,"Medium")=D14,COUNTIFS('Story Mapping'!$H$9:$H$196,A14,'Story Mapping'!$L$9:$L$196,"High")=E14),"OK","MISMATCH") -> OK
A15: Anusharavan Estimation | B15: =C15+D15+E15 -> 4 | C15: =SUM('Anusharavan Estimation'!D8:D9) -> 3 | D15: =SUM('Anusharavan Estimation'!E8:E9) -> 1 | E15: =SUM('Anusharavan Estimation'!F8:F9) -> 0 | F15: ='Anusharavan Estimation'!G10 -> 6 | G15: ='Anusharavan Estimation'!C14 -> 0.19 | H15: ='Anusharavan Estimation'!C16 -> 31.578947 | I15: ='Anusharavan Estimation'!C17 -> 1.01 | J15: ='Anusharavan Estimation'!C20 -> 36.678947 | K15: ='Anusharavan Estimation'!D22 -> 34.845 | L15: ='Anusharavan Estimation'!C22 -> 38.512895 | M15: =IF(AND(COUNTIFS('Story Mapping'!$H$9:$H$196,A15,'Story Mapping'!$L$9:$L$196,"Low")=C15,COUNTIFS('Story Mapping'!$H$9:$H$196,A15,'Story Mapping'!$L$9:$L$196,"Medium")=D15,COUNTIFS('Story Mapping'!$H$9:$H$196,A15,'Story Mapping'!$L$9:$L$196,"High")=E15),"OK","MISMATCH") -> OK
A16: Asset Mapping Estimation | B16: =C16+D16+E16 -> 3 | C16: =SUM('Asset Mapping Estimation'!D8:D9) -> 1 | D16: =SUM('Asset Mapping Estimation'!E8:E9) -> 2 | E16: =SUM('Asset Mapping Estimation'!F8:F9) -> 0 | F16: ='Asset Mapping Estimation'!G10 -> 7 | G16: ='Asset Mapping Estimation'!C14 -> 0.19 | H16: ='Asset Mapping Estimation'!C16 -> 36.842105 | I16: ='Asset Mapping Estimation'!C17 -> 1.01 | J16: ='Asset Mapping Estimation'!C20 -> 42.792105 | K16: ='Asset Mapping Estimation'!D22 -> 40.6525 | L16: ='Asset Mapping Estimation'!C22 -> 44.931711 | M16: =IF(AND(COUNTIFS('Story Mapping'!$H$9:$H$196,A16,'Story Mapping'!$L$9:$L$196,"Low")=C16,COUNTIFS('Story Mapping'!$H$9:$H$196,A16,'Story Mapping'!$L$9:$L$196,"Medium")=D16,COUNTIFS('Story Mapping'!$H$9:$H$196,A16,'Story Mapping'!$L$9:$L$196,"High")=E16),"OK","MISMATCH") -> OK
A17: Bharosa CR Estimation | B17: =C17+D17+E17 -> 3 | C17: =SUM('Bharosa CR Estimation'!D8:D9) -> 2 | D17: =SUM('Bharosa CR Estimation'!E8:E9) -> 1 | E17: =SUM('Bharosa CR Estimation'!F8:F9) -> 0 | F17: ='Bharosa CR Estimation'!G10 -> 5 | G17: ='Bharosa CR Estimation'!C14 -> 0.19 | H17: ='Bharosa CR Estimation'!C16 -> 26.315789 | I17: ='Bharosa CR Estimation'!C17 -> 1.01 | J17: ='Bharosa CR Estimation'!C20 -> 30.565789 | K17: ='Bharosa CR Estimation'!D22 -> 29.0375 | L17: ='Bharosa CR Estimation'!C22 -> 32.094079 | M17: =IF(AND(COUNTIFS('Story Mapping'!$H$9:$H$196,A17,'Story Mapping'!$L$9:$L$196,"Low")=C17,COUNTIFS('Story Mapping'!$H$9:$H$196,A17,'Story Mapping'!$L$9:$L$196,"Medium")=D17,COUNTIFS('Story Mapping'!$H$9:$H$196,A17,'Story Mapping'!$L$9:$L$196,"High")=E17),"OK","MISMATCH") -> OK
A18: AI Module Estimation | B18: =C18+D18+E18 -> 3 | C18: =SUM('AI Module Estimation'!D8:D8) -> 0 | D18: =SUM('AI Module Estimation'!E8:E8) -> 0 | E18: =SUM('AI Module Estimation'!F8:F8) -> 3 | F18: ='AI Module Estimation'!G9 -> 15 | G18: ='AI Module Estimation'!C13 -> 0.19 | H18: ='AI Module Estimation'!C15 -> 78.947368 | I18: ='AI Module Estimation'!C16 -> 1.01 | J18: ='AI Module Estimation'!C19 -> 91.697368 | K18: ='AI Module Estimation'!D21 -> 87.1125 | L18: ='AI Module Estimation'!C21 -> 96.282237 | M18: =IF(AND(COUNTIFS('Story Mapping'!$H$9:$H$196,A18,'Story Mapping'!$L$9:$L$196,"Low")=C18,COUNTIFS('Story Mapping'!$H$9:$H$196,A18,'Story Mapping'!$L$9:$L$196,"Medium")=D18,COUNTIFS('Story Mapping'!$H$9:$H$196,A18,'Story Mapping'!$L$9:$L$196,"High")=E18),"OK","MISMATCH") -> OK
A19: CMMI Doc Estimation | B19: =C19+D19+E19 -> 3 | C19: =SUM('CMMI Doc Estimation'!D8:D9) -> 0 | D19: =SUM('CMMI Doc Estimation'!E8:E9) -> 0 | E19: =SUM('CMMI Doc Estimation'!F8:F9) -> 3 | F19: ='CMMI Doc Estimation'!G10 -> 15 | G19: ='CMMI Doc Estimation'!C14 -> 0.19 | H19: ='CMMI Doc Estimation'!C16 -> 78.947368 | I19: ='CMMI Doc Estimation'!C17 -> 1.01 | J19: ='CMMI Doc Estimation'!C20 -> 91.697368 | K19: ='CMMI Doc Estimation'!D22 -> 87.1125 | L19: ='CMMI Doc Estimation'!C22 -> 96.282237 | M19: =IF(AND(COUNTIFS('Story Mapping'!$H$9:$H$196,A19,'Story Mapping'!$L$9:$L$196,"Low")=C19,COUNTIFS('Story Mapping'!$H$9:$H$196,A19,'Story Mapping'!$L$9:$L$196,"Medium")=D19,COUNTIFS('Story Mapping'!$H$9:$H$196,A19,'Story Mapping'!$L$9:$L$196,"High")=E19),"OK","MISMATCH") -> OK
A20: e-Sign CDAC Estimation | B20: =C20+D20+E20 -> 5 | C20: =SUM('e-Sign CDAC Estimation'!D8:D9) -> 0 | D20: =SUM('e-Sign CDAC Estimation'!E8:E9) -> 2 | E20: =SUM('e-Sign CDAC Estimation'!F8:F9) -> 3 | F20: ='e-Sign CDAC Estimation'!G10 -> 21 | G20: ='e-Sign CDAC Estimation'!C14 -> 0.19 | H20: ='e-Sign CDAC Estimation'!C16 -> 110.52632 | I20: ='e-Sign CDAC Estimation'!C17 -> 1.01 | J20: ='e-Sign CDAC Estimation'!C20 -> 128.37632 | K20: ='e-Sign CDAC Estimation'!D22 -> 121.9575 | L20: ='e-Sign CDAC Estimation'!C22 -> 134.79513 | M20: =IF(AND(COUNTIFS('Story Mapping'!$H$9:$H$196,A20,'Story Mapping'!$L$9:$L$196,"Low")=C20,COUNTIFS('Story Mapping'!$H$9:$H$196,A20,'Story Mapping'!$L$9:$L$196,"Medium")=D20,COUNTIFS('Story Mapping'!$H$9:$H$196,A20,'Story Mapping'!$L$9:$L$196,"High")=E20),"OK","MISMATCH") -> OK
A21: BISAC-BISAG Estimation | B21: =C21+D21+E21 -> 5 | C21: =SUM('BISAC-BISAG Estimation'!D8:D9) -> 0 | D21: =SUM('BISAC-BISAG Estimation'!E8:E9) -> 2 | E21: =SUM('BISAC-BISAG Estimation'!F8:F9) -> 3 | F21: ='BISAC-BISAG Estimation'!G10 -> 21 | G21: ='BISAC-BISAG Estimation'!C14 -> 0.19 | H21: ='BISAC-BISAG Estimation'!C16 -> 110.52632 | I21: ='BISAC-BISAG Estimation'!C17 -> 1.01 | J21: ='BISAC-BISAG Estimation'!C20 -> 128.37632 | K21: ='BISAC-BISAG Estimation'!D22 -> 121.9575 | L21: ='BISAC-BISAG Estimation'!C22 -> 134.79513 | M21: =IF(AND(COUNTIFS('Story Mapping'!$H$9:$H$196,A21,'Story Mapping'!$L$9:$L$196,"Low")=C21,COUNTIFS('Story Mapping'!$H$9:$H$196,A21,'Story Mapping'!$L$9:$L$196,"Medium")=D21,COUNTIFS('Story Mapping'!$H$9:$H$196,A21,'Story Mapping'!$L$9:$L$196,"High")=E21),"OK","MISMATCH") -> OK
A22: Other Modules Estimation | B22: =C22+D22+E22 -> 16 | C22: =SUM('Other Modules Estimation'!D8:D15) -> 2 | D22: =SUM('Other Modules Estimation'!E8:E15) -> 9 | E22: =SUM('Other Modules Estimation'!F8:F15) -> 5 | F22: ='Other Modules Estimation'!G16 -> 54 | G22: ='Other Modules Estimation'!C20 -> 0.19 | H22: ='Other Modules Estimation'!C22 -> 284.21053 | I22: ='Other Modules Estimation'!C23 -> 1.01 | J22: ='Other Modules Estimation'!C26 -> 330.11053 | K22: ='Other Modules Estimation'!D28 -> 313.605 | L22: ='Other Modules Estimation'!C28 -> 346.61605 | M22: =IF(AND(COUNTIFS('Story Mapping'!$H$9:$H$196,A22,'Story Mapping'!$L$9:$L$196,"Low")=C22,COUNTIFS('Story Mapping'!$H$9:$H$196,A22,'Story Mapping'!$L$9:$L$196,"Medium")=D22,COUNTIFS('Story Mapping'!$H$9:$H$196,A22,'Story Mapping'!$L$9:$L$196,"High")=E22),"OK","MISMATCH") -> OK
A23: TOTAL - CYCLE 5 (JUN-SEP 2026) | B23: =SUM(B5:B22) -> 163 | C23: =SUM(C5:C22) -> 46 | D23: =SUM(D5:D22) -> 78 | E23: =SUM(E5:E22) -> 39 | F23: =SUM(F5:F22) -> 475 | G23: ='Baseline Productivity '!C4 -> 0.19 | H23: =SUM(H5:H22) -> 2500 | J23: =SUM(J5:J22) -> 2903.75 | K23: =SUM(K5:K22) -> 2758.5625 | L23: =SUM(L5:L22) -> 3048.9375 | M23: =IF(COUNTIF(M5:M22,"OK")=ROWS(M5:M22),"OK","MISMATCH") -> OK
A25: Reference - hours actually logged (Date-Wise Time Sheet, Jun-Sep 2026)
A26: Jun 2026 (Sprint 17) | B26: 889
A27: Jul 2026 (Sprint 18) | B27: 1133
A28: Aug 2026 (Sprint 19) | B28: 690
A29: Sep 2026 (Sprint 20) | B29: 730
A30: Total hours logged (all activity incl. meetings, adhoc, CMMI) | B30: =SUM(B26:B29) -> 3442
A31: Planned effort / hours logged | B31: =J23/B30 -> 0.84362289
A32: Source: Date_Wise_Time_Sheet (Jun-Sep 2026), hours by entry month. Blue = hardcoded input from the timesheet. The September PSR reports 706.0 hrs against 730.0 hrs in the timesheet file; August matches the PSR (690.0).

Sheet O&M Estimation
B1: Type Of work | C1: Development | D1: New Development
B2: Project Name | C2: Jal Rekha
B3: Remark | C3: O&M Billing Module - Cycle 5 (Jun-Sep 2026)
D5: Volume/Count of elements | H5: Guidelines
A6: Module + sub Module | B6: Functionality ( Sub Module) | C6: Elements (Refer Guidelines and Put here for reference) | D6: Low Complexity | E6: Medium compexity | F6: High Complexity | G6: Size | H6: Low Complexity | I6: Medium compexity | J6: High Complexity
D7: 1 | E7: 3 | F7: 5
A8: O&M Billing - Abstract, Bill PDF & Review | B8: Abstract report, contractor-mistake correction, all-records view, merged bill PDF, landscape fix (Jun-Jul) | C8: US-OM-C5-001 - O&M Billing – Abstract Report Generation [H] US-OM-C5-002 - O&M Billing – Contractor Mistake Correction by SQC/TL → GM [M] US-OM-C5-003 - O&M Billing – Show All Records on All IDs (GM, SQC) [M] US-OM-C5-004 - O&M Billing – Merge PDF of All O&M Bill Documents [M] US-OM-C5-011 - O&M Billing – GM (PIU) Login: Bill PDF (19–20 Docs) & 3-Month Consolidation [M] US-OM-C5-012 - O&M Billing – Sahbhagita Generate Abstract: Select RA Bill & Tag All [M] US-OM-C5-013 - O&M Billing – Landscape Issue Fix in O&M Bill Layout [L] Status: 7 Done | D8: 1 | E8: 5 | F8: 1 | G8: =D8*$D$7+E8*$E$7+F8*$F$7 -> 21
A9: O&M Billing - Power, Construction Bill & Complaints | B9: Power consumption, construction-phase bill columns/villages, pump transformer deduction, residual pressure & complaint redressal (Jun-Jul) | C9: US-OM-C5-005 - O&M Billing – Power Consumption: Contractor & GM Side Changes [H] US-OM-C5-006 - O&M Billing – Two New Columns in Water Supply During Construction Bill [M] US-OM-C5-007 - O&M Billing – O&M Villages: Construction Approval Status [M] US-OM-C5-009 - O&M Billing – GM: Pump Transformer 10% Deduction Logic [M] US-OM-C5-015 - O&M Billing - Residual Pressure & Complaint Redressal Report Format [M] US-OM-C5-016 - O&M Billing - Complaint Redressal: 48-Hour Flag & Penalty Relaxation [L] Status: 4 In Progress, 2 Done | D9: 1 | E9: 4 | F9: 1 | G9: =D9*$D$7+E9*$E$7+F9*$F$7 -> 18
A10: O&M Billing - Dispute, LGD & GST | B10: Contractor dispute window on Dhara data, LGD code integration, GST number (Jun-Jul; also covers Aug restatements AUG-15/16/17) | C10: US-OM-C5-008 - O&M Billing – Aaklan Contractor Dispute: Dhara Data Discrepancy Window [M] US-OM-C5-014 - O&M Billing – LGD Code Integration: LG Directory → MPSQC [M] US-OM-C5-017 - O&M Billing - GST Number Integration [M] Status: 2 In Progress, 1 Open | D10: 0 | E10: 3 | F10: 0 | G10: =D10*$D$7+E10*$E$7+F10*$F$7 -> 9
A11: O&M Billing - WSDCP Phase 1 | B11: New WSDCP tab: payment details, banked-units power sheet, monthly bill sheet, UFW report, pilot UAT (Aug) | C11: US-AUG-01 - O&M Billing — WSDCP - New WSDCP tab and Bill Generation status tracking [H] US-AUG-02 - O&M Billing — WSDCP - WSDCP Payment Details tab [H] US-AUG-03 - O&M Billing — WSDCP - WSDCP Power Consumption Sheet — Banked Units logic [H] US-AUG-04 - O&M Billing — WSDCP - WSDCP Monthly Bill Sheet — Functional HSC and deductions [H] US-AUG-05 - O&M Billing — WSDCP - WSDCP UFW Report (no penalty) [L] US-AUG-06 - O&M Billing — WSDCP - WSDCP User Acceptance Testing on pilot scheme [M] Status: 5 In Progress, 1 Done | D11: 1 | E11: 1 | F11: 4 | G11: =D11*$D$7+E11*$E$7+F11*$F$7 -> 24
A12: O&M Billing - Multi-role Workflow | B12: Forward/backward routing, GM/SQC edit rights with remark, SQC-unavailable fallback, higher-officials chain (Aug) | C12: US-AUG-07 - O&M Billing — Workflow - Full multi-role forward/backward billing workflow [H] US-AUG-08 - O&M Billing — Workflow - GM/SQC edit rights on bill data with mandatory remark [H] US-AUG-09 - O&M Billing — Workflow - SQC-not-available fallback — GM confirms directly [M] US-AUG-10 - O&M Billing — Workflow - Higher Officials approval chain (GM O&M → MD) [H] Status: 4 In Progress | D12: 0 | E12: 1 | F12: 3 | G12: =D12*$D$7+E12*$E$7+F12*$F$7 -> 18
A13: O&M Billing - Data Integrity & Adjustments | B13: Census denominator fix, pending-bills UI, net payable add/deduct, complaint category coding, Aakalan add/deduct (Aug) | C13: US-AUG-11 - O&M Billing — Data Integrity - Census Population / village denominator fix [M] US-AUG-12 - O&M Billing — UI/Workflow - 'Pending Bills for Review' rename and scheme filter [L] US-AUG-13 - O&M Billing — Net Payable - Net Payable Bill — Add More Deduction / Any Other Addition [M] US-AUG-14 - O&M Billing — Complaint Handling - Complaint category coding and extended deductions [M] US-AUG-18 - O&M Billing — Aakalan - Aakalan Addition/Deduction feature (TL SQC / GM PIU) [M] Status: 4 In Progress, 1 Done | D13: 1 | E13: 4 | F13: 0 | G13: =D13*$D$7+E13*$E$7+F13*$F$7 -> 13
A14: O&M Billing / Aaklan - Controls & Tracking | B14: Withheld add/deduct, edit lock, TRP gate, phase tabs, audit trail, role-scoped visibility, validations, user management, complaint carry-forward (Sep) | C14: US-SEP-02 - O&M Billing / Aaklan - Withheld Addition/Deduction amounts shown at End-of-Month [M] US-SEP-03 - O&M Billing / Aaklan - Fix: bill remains editable after Contractor submission [L] US-SEP-04 - O&M Billing / Aaklan - TRP gate controlling O&M Phase availability [L] US-SEP-05 - O&M Billing / Aaklan - Scheme-based SQC/TL list cleanup [L] US-SEP-06 - O&M Billing / Aaklan - WSDCP / TRP / O&M Phase tabs with staged Abstract pages [M] US-SEP-07 - O&M Billing / Aaklan - Full audit trail on Contractor Bill edits [M] US-SEP-08 - O&M Billing / Aaklan - PMC / Deputy O&M role-scoped scheme visibility [M] US-SEP-09 - O&M Billing / Aaklan - Gross Payable Bill — minimum value validation [L] US-SEP-10 - O&M Billing / Aaklan - Census Population verification before Generate Bill [L] US-SEP-11 - O&M Billing / Aaklan - User Management — PIU-wise ID search with Tenure and Agency columns [M] US-SEP-12 - O&M Billing / Aaklan - TL ID conflict resolution (Bhopal / Sehore) [L] US-SEP-13 - O&M Billing / Aaklan - Save-as-Draft confirmation popup on Bulk bill actions [L] US-SEP-14 - O&M Billing — Complaint Redressal - Carry-forward of unresolved complaints with 48-hour flag [M] Status: 6 In Progress, 2 Done, 5 Open | D14: 7 | E14: 6 | F14: 0 | G14: =D14*$D$7+E14*$E$7+F14*$F$7 -> 25
A15: O&M Billing - Contractor/GM UI | B15: Bill Tracking page overhaul, Abstract Bill UI, responsive layout, GM Abstract PDF UI fixes (Sep, PSR/timesheet-sourced) | C15: PSR-SEP-02 - O&M Billing Contractor - Bill Tracking page UI overhaul, Abstract Bill UI, responsive layout [H] PSR-SEP-03 - O&M Billing GM - Abstract Report PDF UI fixes [M] Status: 1 In Progress, 1 Done | D15: 0 | E15: 1 | F15: 1 | G15: =D15*$D$7+E15*$E$7+F15*$F$7 -> 8
A16: TOTAL O&M ESTIMATION (CYCLE 5) | G16: =SUM(G8:G15) -> 136
J17: Value added factors
B18: Total Count | G18: =G16 -> 136 | J18: Factor | L18: Rating
J19: Data Communications | L19: 0
B20: Productivity | C20: ='Baseline Productivity '!$C$4 -> 0.19 | J20: Distributed Data Processing | L20: 0
B21: Size | C21: =G16 -> 136 | D21: Point
B22: Effort | C22: =C21/C20 -> 715.78947 | D22: Man hours | J22: Performance | L22: 0
B23: VAF | C23: =0.65+0.01*$L$35 -> 1.01 | J23: Heavily used Configuration | L23: 3
B24: Risk contingency | C24: 0.05 | J24: Transaction Rate | L24: 4
B25: Project Management | C25: 0.1
B26: Total Planned effort | C26: =C22*C23*(1+C24+C25) -> 831.38947 | D26: Man hours | J26: Online Data Entry | L26: 3
J27: End-User Efficiency | L27: 2
B28: Permissible Range(Man hours) | C28: =C26*1.05 -> 872.95895 | D28: =C26*0.95 -> 789.82 | J28: Online Update | L28: 1
J29: Complex Processing | L29: 3
J30: Reusability | L30: 4
J31: Installation Ease | L31: 4
J32: Operational Ease | L32: 4
J33: Multiple Sites | L33: 4
J34: Facilitate Change | L34: 4
J35: Total | L35: =SUM(L19:L34) -> 36

Sheet Sahbhagita Estimation
B1: Type Of work | C1: Development | D1: New Development
B2: Project Name | C2: Jal Rekha
B3: Remark | C3: Sahbhagita Module - Cycle 5 (Jun-Sep 2026)
D5: Volume/Count of elements | H5: Guidelines
A6: Module + sub Module | B6: Functionality ( Sub Module) | C6: Elements (Refer Guidelines and Put here for reference) | D6: Low Complexity | E6: Medium compexity | F6: High Complexity | G6: Size | H6: Low Complexity | I6: Medium compexity | J6: High Complexity
D7: 1 | E7: 3 | F7: 5
A8: Sahbhagita - RA Bill, Abstract & Reports | B8: RA Bill for ISA, village-wise/combined report, master activity list, RA(1)-RA(12) withhold bills, customised ISA report (Jun) | C8: US-SAH-C5-001 - Sahbhagita – RA Bill for ISA (replacing CP Manager) [M] US-SAH-C5-002 - Sahbhagita – Village-wise & Combined Activity Report [M] US-SAH-C5-003 - Sahbhagita – Master Activity List Update (22 Combined + 32 Village-wise) [M] US-SAH-C5-006 - Sahbhagita – RA Bill: RA(1) till RA(12) Withhold Bills [M] US-SAH-C5-007 - Sahbhagita – Customised Report (ISA – Mainly Contractor Convention) [M] Status: 5 Done | D8: 0 | E8: 5 | F8: 0 | G8: =D8*$D$7+E8*$E$7+F8*$F$7 -> 15
A9: Sahbhagita - UI, Access & Mobile | B9: Hyperlinked document preview, mobile save-as-draft, pagination, FE-to-ISA scoping, ISA password reset (Jun) | C9: US-SAH-C5-005 - Sahbhagita – Hyperlink: Village Name → Village Activity → Document Preview [M] US-SAH-C5-008 - Sahbhagita – Save as Draft for Video, Image & Document (Mobile CR) [M] US-SAH-C5-009 - Sahbhagita - Pagination on Approval Pages [L] US-SAH-C5-010 - Sahbhagita - FE Visibility Scoped to Assigned ISA [L] US-SAH-C5-011 - Sahbhagita - Self-Service Password Reset for ISA Login [L] Status: 5 Done | D9: 3 | E9: 2 | F9: 0 | G9: =D9*$D$7+E9*$E$7+F9*$F$7 -> 9
A10: Sahbhagita - AI Photo Scan | B10: AI face/background detection on activity photos for CP Manager (Jul) | C10: US-SAH-C5-004 - Sahbhagita – Photo Scan AI: Face & Background Detection (CP Manager Review) [H] Status: 1 In Progress | D10: 0 | E10: 0 | F10: 1 | G10: =D10*$D$7+E10*$E$7+F10*$F$7 -> 5
A11: Sahbhagita - Abstract of RA Bill Release | B11: UAT defects DEF-01 to DEF-04, PIU/scheme binding, production release (Aug) | C11: US-AUG-26 - Sahbhagita - Sahbhagita Abstract of RA Bill — production release [L] Status: 1 In Progress | D11: 1 | E11: 0 | F11: 0 | G11: =D11*$D$7+E11*$E$7+F11*$F$7 -> 1
A12: TOTAL SAHBHAGITA ESTIMATION (CYCLE 5) | G12: =SUM(G8:G11) -> 30
J13: Value added factors
B14: Total Count | G14: =G12 -> 30 | J14: Factor | L14: Rating
J15: Data Communications | L15: 0
B16: Productivity | C16: ='Baseline Productivity '!$C$4 -> 0.19 | J16: Distributed Data Processing | L16: 0
B17: Size | C17: =G12 -> 30 | D17: Point
B18: Effort | C18: =C17/C16 -> 157.89474 | D18: Man hours | J18: Performance | L18: 0
B19: VAF | C19: =0.65+0.01*$L$31 -> 1.01 | J19: Heavily used Configuration | L19: 3
B20: Risk contingency | C20: 0.05 | J20: Transaction Rate | L20: 4
B21: Project Management | C21: 0.1
B22: Total Planned effort | C22: =C18*C19*(1+C20+C21) -> 183.39474 | D22: Man hours | J22: Online Data Entry | L22: 3
J23: End-User Efficiency | L23: 2
B24: Permissible Range(Man hours) | C24: =C22*1.05 -> 192.56447 | D24: =C22*0.95 -> 174.225 | J24: Online Update | L24: 1
J25: Complex Processing | L25: 3
J26: Reusability | L26: 4
J27: Installation Ease | L27: 4
J28: Operational Ease | L28: 4
J29: Multiple Sites | L29: 4
J30: Facilitate Change | L30: 4
J31: Total | L31: =SUM(L15:L30) -> 36

Sheet Dhara Estimation
B1: Type Of work | C1: Development | D1: New Development
B2: Project Name | C2: Jal Rekha
B3: Remark | C3: Dhara Module - Cycle 5 (Jun-Sep 2026)
D5: Volume/Count of elements | H5: Guidelines
A6: Module + sub Module | B6: Functionality ( Sub Module) | C6: Elements (Refer Guidelines and Put here for reference) | D6: Low Complexity | E6: Medium compexity | F6: High Complexity | G6: Size | H6: Low Complexity | I6: Medium compexity | J6: High Complexity
D7: 1 | E7: 3 | F7: 5
A8: Dhara - Reports & Approved Data | B8: Report corrections, 27-May format, contractor dispute window, new reports on all logins, base-capacity columns, approved-data correction (Jun-Jul) | C8: US-DHR-C5-001 - Dhara – Report Corrections (Approved Village MWSR, DWSR, OHT) [M] US-DHR-C5-002 - Dhara – Report Format Standardisation (27 May 2026 Format) [M] US-DHR-C5-003 - Dhara – Approved Reports & Contractor Dispute Window [M] US-DHR-C5-004 - Dhara – New Dhara Reports Visible on All Jal Rekha Logins [M] US-DHR-C5-006 - Dhara – OHT/WTP/Intake Base Capacity Column in Report [M] US-DHR-C5-007 - Dhara - Approved Report Data Correction (Agreed with Kapil Sir) [M] Status: 4 Done, 2 In Progress | D8: 0 | E8: 6 | F8: 0 | G8: =D8*$D$7+E8*$E$7+F8*$F$7 -> 18
A9: Dhara - Entry Lock & Optional Fields | B9: Approved entry lock; non-mandatory remark/photo/forward/backward (Jun) | C9: US-DHR-C5-005 - Dhara – Dhara Entry Lock (Approved Data Should Not Change) [M] US-DHR-C5-008 - Dhara - Non-Mandatory Remark, Photo Upload, Forward & Backward Options [L] Status: 2 Done | D9: 1 | E9: 1 | F9: 0 | G9: =D9*$D$7+E9*$E$7+F9*$F$7 -> 4
A10: Dhara - Meter Logic & Sequential Approval | B10: FE/Dhara meter functional logic, sequential month-wise approval lock (Aug-Sep) | C10: US-AUG-22 - SVS / Dhara Meter Logic - FE/Dhara Meter Functional logic and sequential approval [M] US-SEP-15 - Dhara - Dhara sequential reading approval lock [M] Status: 2 In Progress | D10: 0 | E10: 2 | F10: 0 | G10: =D10*$D$7+E10*$E$7+F10*$F$7 -> 6
A11: Dhara - Edit Rules, Survey Report & MPEB API | B11: Reading edit rules by meter status, survey report column restructuring, MPEB smart-meter API (Sep) | C11: US-SEP-16 - Dhara - Dhara reading edit rules by meter status (GM / SQC-TL login) [H] US-SEP-17 - Dhara - Dhara Survey Report column restructuring [M] US-SEP-18 - Dhara - Dhara Electricity Meter Bill — MPEB Smart Meter API integration [H] Status: 3 Open | D11: 0 | E11: 1 | F11: 2 | G11: =D11*$D$7+E11*$E$7+F11*$F$7 -> 13
A12: Dhara & Nirmal - Panchayat Monitoring | B12: Panchayat-level dashboards for Dhara and Nirmal; 5-step MVS-to-local-body handover (Aug) | C12: US-AUG-34 - Dhara & Nirmal Panchayat Monitoring - Panchayat-level dashboard and MVS-to-local-body handover [H] Status: 1 In Progress | D12: 0 | E12: 0 | F12: 1 | G12: =D12*$D$7+E12*$E$7+F12*$F$7 -> 5
A13: TOTAL DHARA ESTIMATION (CYCLE 5) | G13: =SUM(G8:G12) -> 46
J14: Value added factors
B15: Total Count | G15: =G13 -> 46 | J15: Factor | L15: Rating
J16: Data Communications | L16: 0
B17: Productivity | C17: ='Baseline Productivity '!$C$4 -> 0.19 | J17: Distributed Data Processing | L17: 0
B18: Size | C18: =G13 -> 46 | D18: Point
B19: Effort | C19: =C18/C17 -> 242.10526 | D19: Man hours | J19: Performance | L19: 0
B20: VAF | C20: =0.65+0.01*$L$32 -> 1.01 | J20: Heavily used Configuration | L20: 3
B21: Risk contingency | C21: 0.05 | J21: Transaction Rate | L21: 4
B22: Project Management | C22: 0.1
B23: Total Planned effort | C23: =C19*C20*(1+C21+C22) -> 281.20526 | D23: Man hours | J23: Online Data Entry | L23: 3
J24: End-User Efficiency | L24: 2
B25: Permissible Range(Man hours) | C25: =C23*1.05 -> 295.26553 | D25: =C23*0.95 -> 267.145 | J25: Online Update | L25: 1
J26: Complex Processing | L26: 3
J27: Reusability | L27: 4
J28: Installation Ease | L28: 4
J29: Operational Ease | L29: 4
J30: Multiple Sites | L30: 4
J31: Facilitate Change | L31: 4
J32: Total | L32: =SUM(L16:L31) -> 36

Sheet Master Estimation
B1: Type Of work | C1: Development | D1: New Development
B2: Project Name | C2: Jal Rekha
B3: Remark | C3: Master / Vistrit Module - Cycle 5 (Jun-Sep 2026)
D5: Volume/Count of elements | H5: Guidelines
A6: Module + sub Module | B6: Functionality ( Sub Module) | C6: Elements (Refer Guidelines and Put here for reference) | D6: Low Complexity | E6: Medium compexity | F6: High Complexity | G6: Size | H6: Low Complexity | I6: Medium compexity | J6: High Complexity
D7: 1 | E7: 3 | F7: 5
A8: Vistrit - Mapping, OTP & Validation | B8: WTP meter mapping columns, OTP on GM edit/delete, field validation, OHT deactivate fix, meter naming, duplicate-village validation (Jun) | C8: US-VST-C5-001 - Vistrit – WTP Meter Mapping: New Columns (Date, Scheme, PIU, Meter Name) [M] US-VST-C5-002 - Vistrit – OTP Verification for GM Edit/Delete on Scheme, OHT, Bulk Master [M] US-VST-C5-003 - Vistrit – Scheme Village Mapping: Testing/Permitted Field Validation & Census Population [L] US-VST-C5-004 - Vistrit – OHT Deactivate Bug Fix (OHT Not Visible in FE Login) [M] US-VST-C5-005 - Vistrit – WTP Meter Naming Convention Standardisation [L] US-VST-OTP-C5-002 - Vistrit – Scheme Village Mapping: Duplicate Village Validation [L] Status: 6 Done | D8: 3 | E8: 3 | F8: 0 | G8: =D8*$D$7+E8*$E$7+F8*$F$7 -> 12
A9: Master - Lock & Data Integrity | B9: Lock Scheme/Village/OHT master on live link (CR MSTR-JUN-2026-006), Dhara mapped summary search fix, village deletion restriction (Jun-Jul) | C9: US-MSTR-C5-001 - Master - Lock Scheme/Village/OHT Master Once Linked to Live Transactions [M] US-MSTR-C5-002 - Master - Dhara Mapped Summary Report Search Debugging & Enhancement [M] US-MSTR-C5-003 - Master - Village Deletion Restriction & Database Validation Message [L] Status: 1 Open, 2 Done | D9: 1 | E9: 2 | F9: 0 | G9: =D9*$D$7+E9*$E$7+F9*$F$7 -> 7
A10: Vistrit - Survey Intake/WTP/OHT Master | B10: Three new master sub-modules with Add/Update action (Sep) | C10: US-SEP-25 - Vistrit (Master) - Survey Intake, WTP and OHT Master sub-modules [M] Status: 1 In Progress | D10: 0 | E10: 1 | F10: 0 | G10: =D10*$D$7+E10*$E$7+F10*$F$7 -> 3
A11: TOTAL MASTER ESTIMATION (CYCLE 5) | G11: =SUM(G8:G10) -> 22
J12: Value added factors
B13: Total Count | G13: =G11 -> 22 | J13: Factor | L13: Rating
J14: Data Communications | L14: 0
B15: Productivity | C15: ='Baseline Productivity '!$C$4 -> 0.19 | J15: Distributed Data Processing | L15: 0
B16: Size | C16: =G11 -> 22 | D16: Point
B17: Effort | C17: =C16/C15 -> 115.78947 | D17: Man hours | J17: Performance | L17: 0
B18: VAF | C18: =0.65+0.01*$L$30 -> 1.01 | J18: Heavily used Configuration | L18: 3
B19: Risk contingency | C19: 0.05 | J19: Transaction Rate | L19: 4
B20: Project Management | C20: 0.1
B21: Total Planned effort | C21: =C17*C18*(1+C19+C20) -> 134.48947 | D21: Man hours | J21: Online Data Entry | L21: 3
J22: End-User Efficiency | L22: 2
B23: Permissible Range(Man hours) | C23: =C21*1.05 -> 141.21395 | D23: =C21*0.95 -> 127.765 | J23: Online Update | L23: 1
J24: Complex Processing | L24: 3
J25: Reusability | L25: 4
J26: Installation Ease | L26: 4
J27: Operational Ease | L27: 4
J28: Multiple Sites | L28: 4
J29: Facilitate Change | L29: 4
J30: Total | L30: =SUM(L14:L29) -> 36

Sheet FHTC Estimation
B1: Type Of work | C1: Development | D1: New Development
B2: Project Name | C2: Jal Rekha
B3: Remark | C3: FHTC / Parinam Module - Cycle 5 (Jun-Sep 2026)
D5: Volume/Count of elements | H5: Guidelines
A6: Module + sub Module | B6: Functionality ( Sub Module) | C6: Elements (Refer Guidelines and Put here for reference) | D6: Low Complexity | E6: Medium compexity | F6: High Complexity | G6: Size | H6: Low Complexity | I6: Medium compexity | J6: High Complexity
D7: 1 | E7: 3 | F7: 5
A8: FHTC Parinam - Nasamajh, Samagra & Surveys | B8: Nasamajh family head ID, Samagra API integration, multiple surveys per Samagra ID (Jun-Jul) | C8: US-FHTC-C5-001 - FHTC Parinam – Nasamajh Family Head ID & Add Connection [M] US-FHTC-C5-004 - FHTC Parinam – Samagra API Integration for Household Data [H] US-FHTC-C5-005 - FHTC Parinam - Multiple Surveys per Samagra ID [M] Status: 2 In Progress, 1 Done | D8: 0 | E8: 2 | F8: 1 | G8: =D8*$D$7+E8*$E$7+F8*$F$7 -> 11
A9: FHTC Parinam - Reports & Search | B9: FE name in reports, contractor search option (Jun) | C9: US-FHTC-C5-002 - FHTC Parinam – FE Name Shown in Reports [L] US-FHTC-C5-003 - FHTC Parinam – Contractor Search Option [L] Status: 2 Done | D9: 2 | E9: 0 | F9: 0 | G9: =D9*$D$7+E9*$E$7+F9*$F$7 -> 2
A10: FHTC Parinam - Dashboard | B10: Parinam Dashboard tab on HSC Survey screen; FE dashboard and FE-login reports in mobile APK (Aug-Sep) | C10: US-AUG-27 - FHTC / Parinam - Parinam Dashboard tab on HSC Survey screen [L] US-SEP-26 - Parinam - FE dashboard, FE-login reports, and multi-survey support confirmed stable [L] Status: 2 Done | D10: 2 | E10: 0 | F10: 0 | G10: =D10*$D$7+E10*$E$7+F10*$F$7 -> 2
A11: TOTAL FHTC ESTIMATION (CYCLE 5) | G11: =SUM(G8:G10) -> 15
J12: Value added factors
B13: Total Count | G13: =G11 -> 15 | J13: Factor | L13: Rating
J14: Data Communications | L14: 0
B15: Productivity | C15: ='Baseline Productivity '!$C$4 -> 0.19 | J15: Distributed Data Processing | L15: 0
B16: Size | C16: =G11 -> 15 | D16: Point
B17: Effort | C17: =C16/C15 -> 78.947368 | D17: Man hours | J17: Performance | L17: 0
B18: VAF | C18: =0.65+0.01*$L$30 -> 1.01 | J18: Heavily used Configuration | L18: 3
B19: Risk contingency | C19: 0.05 | J19: Transaction Rate | L19: 4
B20: Project Management | C20: 0.1
B21: Total Planned effort | C21: =C17*C18*(1+C19+C20) -> 91.697368 | D21: Man hours | J21: Online Data Entry | L21: 3
J22: End-User Efficiency | L22: 2
B23: Permissible Range(Man hours) | C23: =C21*1.05 -> 96.282237 | D23: =C21*0.95 -> 87.1125 | J23: Online Update | L23: 1
J24: Complex Processing | L24: 3
J25: Reusability | L25: 4
J26: Installation Ease | L26: 4
J27: Operational Ease | L27: 4
J28: Multiple Sites | L28: 4
J29: Facilitate Change | L29: 4
J30: Total | L30: =SUM(L14:L29) -> 36

Sheet Cube Testing Estimation
B1: Type Of work | C1: Development | D1: New Development
B2: Project Name | C2: Jal Rekha
B3: Remark | C3: Cube Testing Module - Cycle 5 (Jun-Sep 2026)
D5: Volume/Count of elements | H5: Guidelines
A6: Module + sub Module | B6: Functionality ( Sub Module) | C6: Elements (Refer Guidelines and Put here for reference) | D6: Low Complexity | E6: Medium compexity | F6: High Complexity | G6: Size | H6: Low Complexity | I6: Medium compexity | J6: High Complexity
D7: 1 | E7: 3 | F7: 5
A8: Cube Testing - Contractor Visibility & ID | B8: Rejected data to contractor, Cube ID before image upload, Filter Bed sub-component (Jun) | C8: US-CUBE-C5-001 - Cube Testing – Show Rejected Data to Contractor [L] US-CUBE-C5-002 - Cube Testing – Cube ID Generated Before Image Upload [L] US-CUBE-C5-003 - Cube Testing – Filter Bed Sub-Component Under WTP [L] Status: 3 Done | D8: 3 | E8: 0 | F8: 0 | G8: =D8*$D$7+E8*$E$7+F8*$F$7 -> 3
A9: Cube Testing - Re-Inspection Loop | B9: 2nd-loop re-inspection after GM rejection; optional image on 2nd RFI loop (Jul) | C9: US-CUBE-C5-004 - Cube Testing - Re-Inspection Loop (2nd Loop after GM Rejection) [M] US-CUBE-C5-005 - Cube Testing - Optional Image Upload on Second RFI Loop [L] Status: 2 Done | D9: 1 | E9: 1 | F9: 0 | G9: =D9*$D$7+E9*$E$7+F9*$F$7 -> 4
A10: Cube Testing - Re-Inspection Status | B10: Cube RFI Id display; colour flag and separate re-inspection status (Sep) | C10: US-SEP-20 - Cube Testing - Cube RFI Id display [L] US-SEP-21 - Cube Testing - Cube Reinspection — colour flag and separate status [L] Status: 1 Open, 1 In Progress | D10: 2 | E10: 0 | F10: 0 | G10: =D10*$D$7+E10*$E$7+F10*$F$7 -> 2
A11: TOTAL CUBE TESTING ESTIMATION (CYCLE 5) | G11: =SUM(G8:G10) -> 9
J12: Value added factors
B13: Total Count | G13: =G11 -> 9 | J13: Factor | L13: Rating
J14: Data Communications | L14: 0
B15: Productivity | C15: ='Baseline Productivity '!$C$4 -> 0.19 | J15: Distributed Data Processing | L15: 0
B16: Size | C16: =G11 -> 9 | D16: Point
B17: Effort | C17: =C16/C15 -> 47.368421 | D17: Man hours | J17: Performance | L17: 0
B18: VAF | C18: =0.65+0.01*$L$30 -> 1.01 | J18: Heavily used Configuration | L18: 3
B19: Risk contingency | C19: 0.05 | J19: Transaction Rate | L19: 4
B20: Project Management | C20: 0.1
B21: Total Planned effort | C21: =C17*C18*(1+C19+C20) -> 55.018421 | D21: Man hours | J21: Online Data Entry | L21: 3
J22: End-User Efficiency | L22: 2
B23: Permissible Range(Man hours) | C23: =C21*1.05 -> 57.769342 | D23: =C21*0.95 -> 52.2675 | J23: Online Update | L23: 1
J24: Complex Processing | L24: 3
J25: Reusability | L25: 4
J26: Installation Ease | L26: 4
J27: Operational Ease | L27: 4
J28: Multiple Sites | L28: 4
J29: Facilitate Change | L29: 4
J30: Total | L30: =SUM(L14:L29) -> 36

Sheet Material Testing Estimation
B1: Type Of work | C1: Development | D1: New Development
B2: Project Name | C2: Jal Rekha
B3: Remark | C3: Material Testing - Cycle 5 (Jun-Sep 2026)
D5: Volume/Count of elements | H5: Guidelines
A6: Module + sub Module | B6: Functionality ( Sub Module) | C6: Elements (Refer Guidelines and Put here for reference) | D6: Low Complexity | E6: Medium compexity | F6: High Complexity | G6: Size | H6: Low Complexity | I6: Medium compexity | J6: High Complexity
D7: 1 | E7: 3 | F7: 5
A8: Material Testing - Re-Inspection Loop | B8: 2nd-loop re-inspection and optional image on 2nd RFI loop (Jul-Aug; the AUG-25 production deployment is covered by these stories) | C8: US-MAT-C5-001 - Material Testing - Re-Inspection Loop (2nd Loop after GM Rejection) [M] US-MAT-C5-002 - Material Testing - Optional Image Upload on Second RFI Loop [L] Status: 1 In Progress, 1 Open | D8: 1 | E8: 1 | F8: 0 | G8: =D8*$D$7+E8*$E$7+F8*$F$7 -> 4
A9: Material Testing - GM/Contractor DB & API | B9: Database functions and API enhancements for re-inspection (Jul) | C9: US-MAT-C5-003 - Material Testing - GM/Contractor Login Database & API Enhancements [H] Status: 1 In Progress | D9: 0 | E9: 0 | F9: 1 | G9: =D9*$D$7+E9*$E$7+F9*$F$7 -> 5
A10: Material Testing - Re-Inspection Id Flag | B10: Separate flag status for Material Reinspection Id (Sep) | C10: US-SEP-22 - Material Testing - Material Reinspection Id — separate flag status [L] Status: 1 In Progress | D10: 1 | E10: 0 | F10: 0 | G10: =D10*$D$7+E10*$E$7+F10*$F$7 -> 1
A11: TOTAL MATERIAL TESTING ESTIMATION (CYCLE 5) | G11: =SUM(G8:G10) -> 10
J12: Value added factors
B13: Total Count | G13: =G11 -> 10 | J13: Factor | L13: Rating
J14: Data Communications | L14: 0
B15: Productivity | C15: ='Baseline Productivity '!$C$4 -> 0.19 | J15: Distributed Data Processing | L15: 0
B16: Size | C16: =G11 -> 10 | D16: Point
B17: Effort | C17: =C16/C15 -> 52.631579 | D17: Man hours | J17: Performance | L17: 0
B18: VAF | C18: =0.65+0.01*$L$30 -> 1.01 | J18: Heavily used Configuration | L18: 3
B19: Risk contingency | C19: 0.05 | J19: Transaction Rate | L19: 4
B20: Project Management | C20: 0.1
B21: Total Planned effort | C21: =C17*C18*(1+C19+C20) -> 61.131579 | D21: Man hours | J21: Online Data Entry | L21: 3
J22: End-User Efficiency | L22: 2
B23: Permissible Range(Man hours) | C23: =C21*1.05 -> 64.188158 | D23: =C21*0.95 -> 58.075 | J23: Online Update | L23: 1
J24: Complex Processing | L24: 3
J25: Reusability | L25: 4
J26: Installation Ease | L26: 4
J27: Operational Ease | L27: 4
J28: Multiple Sites | L28: 4
J29: Facilitate Change | L29: 4
J30: Total | L30: =SUM(L14:L29) -> 36

Sheet Nirmal Estimation
B1: Type Of work | C1: Development | D1: New Development
B2: Project Name | C2: Jal Rekha
B3: Remark | C3: Nirmal Module - Cycle 5 (Jun-Sep 2026)
D5: Volume/Count of elements | H5: Guidelines
A6: Module + sub Module | B6: Functionality ( Sub Module) | C6: Elements (Refer Guidelines and Put here for reference) | D6: Low Complexity | E6: Medium compexity | F6: High Complexity | G6: Size | H6: Low Complexity | I6: Medium compexity | J6: High Complexity
D7: 1 | E7: 3 | F7: 5
A8: Nirmal - Reports & Bug Fixes | B8: Beneficiary report fix, contractor counting bug, FE mobile reports, test scenarios/cases (Jun) | C8: US-NRM-C5-001 - Nirmal - Beneficiary Report Issue Fix [M] US-NRM-C5-002 - Nirmal - Contractor Login Report Counting Bug Fix [L] US-NRM-C5-003 - Nirmal - FE Mobile Reports Validation & Bug Fixes [M] US-NRM-C5-004 - Nirmal - Test Scenario and Test Case Creation [L] Status: 4 Done | D8: 2 | E8: 2 | F8: 0 | G8: =D8*$D$7+E8*$E$7+F8*$F$7 -> 8
A9: Nirmal / SVS PHE - Water Testing | B9: SVS PHE status labelling and approval lock; water-testing entry form with pass/fail logic (Aug) | C9: US-AUG-23 - Nirmal / SVS PHE - Nirmal/SVS PHE integration logic and status labelling [M] US-AUG-24 - Nirmal / SVS PHE - Nirmal/SVS PHE water-testing entry form [H] Status: 2 In Progress | D9: 0 | E9: 1 | F9: 1 | G9: =D9*$D$7+E9*$E$7+F9*$F$7 -> 8
A10: TOTAL NIRMAL ESTIMATION (CYCLE 5) | G10: =SUM(G8:G9) -> 16
J11: Value added factors
B12: Total Count | G12: =G10 -> 16 | J12: Factor | L12: Rating
J13: Data Communications | L13: 0
B14: Productivity | C14: ='Baseline Productivity '!$C$4 -> 0.19 | J14: Distributed Data Processing | L14: 0
B15: Size | C15: =G10 -> 16 | D15: Point
B16: Effort | C16: =C15/C14 -> 84.210526 | D16: Man hours | J16: Performance | L16: 0
B17: VAF | C17: =0.65+0.01*$L$29 -> 1.01 | J17: Heavily used Configuration | L17: 3
B18: Risk contingency | C18: 0.05 | J18: Transaction Rate | L18: 4
B19: Project Management | C19: 0.1
B20: Total Planned effort | C20: =C16*C17*(1+C18+C19) -> 97.810526 | D20: Man hours | J20: Online Data Entry | L20: 3
J21: End-User Efficiency | L21: 2
B22: Permissible Range(Man hours) | C22: =C20*1.05 -> 102.70105 | D22: =C20*0.95 -> 92.92 | J22: Online Update | L22: 1
J23: Complex Processing | L23: 3
J24: Reusability | L24: 4
J25: Installation Ease | L25: 4
J26: Operational Ease | L26: 4
J27: Multiple Sites | L27: 4
J28: Facilitate Change | L28: 4
J29: Total | L29: =SUM(L13:L28) -> 36

Sheet SVS Estimation
B1: Type Of work | C1: Development | D1: New Development
B2: Project Name | C2: Jal Rekha
B3: Remark | C3: SVS Water Supply Monitoring - Cycle 5 (Jun-Sep 2026)
D5: Volume/Count of elements | H5: Guidelines
A6: Module + sub Module | B6: Functionality ( Sub Module) | C6: Elements (Refer Guidelines and Put here for reference) | D6: Low Complexity | E6: Medium compexity | F6: High Complexity | G6: Size | H6: Low Complexity | I6: Medium compexity | J6: High Complexity
D7: 1 | E7: 3 | F7: 5
A8: SVS - Daily Water Supply Entry | B8: Bilingual conversion, login-scoped District/Block/GP, additional No-Supply reason, JJM ID removal (Jun) | C8: US-SVS-C5-001 - SVS – Bilingual Conversion (Hindi/English) for Water Supply Entry Page [M] US-SVS-C5-002 - SVS – Login-Specific District, Block, GP Auto-Selection [L] US-SVS-C5-003 - SVS – Additional Reason for NO Supply & Spelling Correction [L] US-SVS-C5-004 - SVS – Remove JJM ID and Village Status Fields [L] Status: 4 Done | D8: 3 | E8: 1 | F8: 0 | G8: =D8*$D$7+E8*$E$7+F8*$F$7 -> 6
A9: SVS - Dashboard V2 & Drill-down | B9: KPI cards with colour coding; Gram Sachiv and CEO/CO Block drill-down (Aug) | C9: US-AUG-19 - SVS Water Supply Dashboard - SVS Water Supply Status Dashboard V2 — KPI cards and colour coding [H] US-AUG-20 - SVS Water Supply Dashboard - SVS dashboard drill-down — Gram Sachiv and CEO/CO Block [H] Status: 2 In Progress | D9: 0 | E9: 0 | F9: 2 | G9: =D9*$D$7+E9*$E$7+F9*$F$7 -> 10
A10: SVS / MVS - Master | B10: SVS master wireframe and MVS Master for 600+ schemes (Aug) | C10: US-AUG-21 - SVS / MVS Master - SVS master wireframe and MVS Master (600+ entries) [M] Status: 1 In Progress | D10: 0 | E10: 1 | F10: 0 | G10: =D10*$D$7+E10*$E$7+F10*$F$7 -> 3
A11: SVS Nirmal - FTK Kit | B11: FTK kit report and SVS Nirmal wireframe (Sep) | C11: US-SEP-28 - SVS Nirmal - FTK kit report and SVS Nirmal wireframe [L] Status: 1 Done | D11: 1 | E11: 0 | F11: 0 | G11: =D11*$D$7+E11*$E$7+F11*$F$7 -> 1
A12: TOTAL SVS ESTIMATION (CYCLE 5) | G12: =SUM(G8:G11) -> 20
J13: Value added factors
B14: Total Count | G14: =G12 -> 20 | J14: Factor | L14: Rating
J15: Data Communications | L15: 0
B16: Productivity | C16: ='Baseline Productivity '!$C$4 -> 0.19 | J16: Distributed Data Processing | L16: 0
B17: Size | C17: =G12 -> 20 | D17: Point
B18: Effort | C18: =C17/C16 -> 105.26316 | D18: Man hours | J18: Performance | L18: 0
B19: VAF | C19: =0.65+0.01*$L$31 -> 1.01 | J19: Heavily used Configuration | L19: 3
B20: Risk contingency | C20: 0.05 | J20: Transaction Rate | L20: 4
B21: Project Management | C21: 0.1
B22: Total Planned effort | C22: =C18*C19*(1+C20+C21) -> 122.26316 | D22: Man hours | J22: Online Data Entry | L22: 3
J23: End-User Efficiency | L23: 2
B24: Permissible Range(Man hours) | C24: =C22*1.05 -> 128.37632 | D24: =C22*0.95 -> 116.15 | J24: Online Update | L24: 1
J25: Complex Processing | L25: 3
J26: Reusability | L26: 4
J27: Installation Ease | L27: 4
J28: Operational Ease | L28: 4
J29: Multiple Sites | L29: 4
J30: Facilitate Change | L30: 4
J31: Total | L31: =SUM(L15:L30) -> 36

Sheet SVS Anusharavan GP Estimation
B1: Type Of work | C1: Development | D1: New Development
B2: Project Name | C2: Jal Rekha
B3: Remark | C3: SVS Anusharavan GP Module - Cycle 5 (Aug-Sep 2026)
D5: Volume/Count of elements | H5: Guidelines
A6: Module + sub Module | B6: Functionality ( Sub Module) | C6: Elements (Refer Guidelines and Put here for reference) | D6: Low Complexity | E6: Medium compexity | F6: High Complexity | G6: Size | H6: Low Complexity | I6: Medium compexity | J6: High Complexity
D7: 1 | E7: 3 | F7: 5
A8: SVS Anusharavan GP - Master & Wireframe | B8: GP Master, Anusharavan GP wireframe, user management; funds-source and work-type masters (Sep) | C8: US-SEP-29 - SVS Anusharavan GP - GP Master and Anusharavan GP wireframe and user management [M] US-SEP-34 - GP Master Data - Gram Panchayat Funds-Source and Nirman Karya work-type masters [M] Status: 1 Done, 1 Open | D8: 0 | E8: 2 | F8: 0 | G8: =D8*$D$7+E8*$E$7+F8*$F$7 -> 6
A9: SVS Anusharavan GP - Mobile & RFI Workflow | B9: Simplified RFI, GP mobile screen for FE, GP RFI raise and Sub-Engineer review (Aug-Sep) | C9: US-AUG-35 - RFI / Anusharavan (SVS-GP) - Simplified RFI system and GP–FE review workflow [H] US-SEP-30 - SVS Anusharavan GP - GP Anusharavan Mobile Screen for FE [M] US-SEP-31 - Anusharavan SVS — RFI - Gram Panchayat RFI raise and Sub-Engineer review workflow [H] Status: 1 Not Started, 1 In Progress, 1 Open | D9: 0 | E9: 1 | F9: 2 | G9: =D9*$D$7+E9*$E$7+F9*$F$7 -> 13
A10: SVS Anusharavan GP - SIPRI Integration | B10: SIPRI/NREGA/Yuktdhara integration; AE block-wise login and Panchayat ID whitelisting (Sep) | C10: US-SEP-32 - Anusharavan SVS — SIPRI Integration - SIPRI / NREGA / Yuktdhara integration for GP works planning [H] US-SEP-33 - Anusharavan SVS — SIPRI Integration - SIPRI AE block-wise login and Panchayat ID whitelisting [M] Status: 2 Open | D10: 0 | E10: 1 | F10: 1 | G10: =D10*$D$7+E10*$E$7+F10*$F$7 -> 8
A11: TOTAL SVS ANUSHARAVAN GP ESTIMATION (CYCLE 5) | G11: =SUM(G8:G10) -> 27
J12: Value added factors
B13: Total Count | G13: =G11 -> 27 | J13: Factor | L13: Rating
J14: Data Communications | L14: 0
B15: Productivity | C15: ='Baseline Productivity '!$C$4 -> 0.19 | J15: Distributed Data Processing | L15: 0
B16: Size | C16: =G11 -> 27 | D16: Point
B17: Effort | C17: =C16/C15 -> 142.10526 | D17: Man hours | J17: Performance | L17: 0
B18: VAF | C18: =0.65+0.01*$L$30 -> 1.01 | J18: Heavily used Configuration | L18: 3
B19: Risk contingency | C19: 0.05 | J19: Transaction Rate | L19: 4
B20: Project Management | C20: 0.1
B21: Total Planned effort | C21: =C17*C18*(1+C19+C20) -> 165.05526 | D21: Man hours | J21: Online Data Entry | L21: 3
J22: End-User Efficiency | L22: 2
B23: Permissible Range(Man hours) | C23: =C21*1.05 -> 173.30803 | D23: =C21*0.95 -> 156.8025 | J23: Online Update | L23: 1
J24: Complex Processing | L24: 3
J25: Reusability | L25: 4
J26: Installation Ease | L26: 4
J27: Operational Ease | L27: 4
J28: Multiple Sites | L28: 4
J29: Facilitate Change | L29: 4
J30: Total | L30: =SUM(L14:L29) -> 36

Sheet Anusharavan Estimation
B1: Type Of work | C1: Development | D1: New Development
B2: Project Name | C2: Jal Rekha
B3: Remark | C3: Anusharavan Module - Cycle 5 (Jun-Sep 2026)
D5: Volume/Count of elements | H5: Guidelines
A6: Module + sub Module | B6: Functionality ( Sub Module) | C6: Elements (Refer Guidelines and Put here for reference) | D6: Low Complexity | E6: Medium compexity | F6: High Complexity | G6: Size | H6: Low Complexity | I6: Medium compexity | J6: High Complexity
D7: 1 | E7: 3 | F7: 5
A8: Anusharavan - RFI Reports & Search | B8: Multi-date in report, OHT search during RFI, optional GPS/village for Intake/WTP/MBR/RWPM (Jun) | C8: US-ANS-C5-001 - Anusharavan – Multi-Date in Report: FE RFI Submission Date & Block Name [M] US-ANS-C5-002 - Anusharavan – OHT Search Option During RFI [L] US-ANS-C5-003 - Anusharavan – Remove Mandatory GPS/Village for Intake, WTP, MBR, RWPM, CWPM [L] Status: 3 Done | D8: 2 | E8: 1 | F8: 0 | G8: =D8*$D$7+E8*$E$7+F8*$F$7 -> 5
A9: Anusharavan - Survey Fix | B9: Fix multiple survey submission by SQC/TL (Sep) | C9: US-SEP-24 - Anusharavan - Fix: multiple survey submission by SQC/TL [L] Status: 1 In Progress | D9: 1 | E9: 0 | F9: 0 | G9: =D9*$D$7+E9*$E$7+F9*$F$7 -> 1
A10: TOTAL ANUSHARAVAN ESTIMATION (CYCLE 5) | G10: =SUM(G8:G9) -> 6
J11: Value added factors
B12: Total Count | G12: =G10 -> 6 | J12: Factor | L12: Rating
J13: Data Communications | L13: 0
B14: Productivity | C14: ='Baseline Productivity '!$C$4 -> 0.19 | J14: Distributed Data Processing | L14: 0
B15: Size | C15: =G10 -> 6 | D15: Point
B16: Effort | C16: =C15/C14 -> 31.578947 | D16: Man hours | J16: Performance | L16: 0
B17: VAF | C17: =0.65+0.01*$L$29 -> 1.01 | J17: Heavily used Configuration | L17: 3
B18: Risk contingency | C18: 0.05 | J18: Transaction Rate | L18: 4
B19: Project Management | C19: 0.1
B20: Total Planned effort | C20: =C16*C17*(1+C18+C19) -> 36.678947 | D20: Man hours | J20: Online Data Entry | L20: 3
J21: End-User Efficiency | L21: 2
B22: Permissible Range(Man hours) | C22: =C20*1.05 -> 38.512895 | D22: =C20*0.95 -> 34.845 | J22: Online Update | L22: 1
J23: Complex Processing | L23: 3
J24: Reusability | L24: 4
J25: Installation Ease | L25: 4
J26: Operational Ease | L26: 4
J27: Multiple Sites | L27: 4
J28: Facilitate Change | L28: 4
J29: Total | L29: =SUM(L13:L28) -> 36

Sheet Asset Mapping Estimation
B1: Type Of work | C1: Development | D1: New Development
B2: Project Name | C2: Jal Rekha
B3: Remark | C3: Asset Mapping Module - Cycle 5 (Jun-Sep 2026)
D5: Volume/Count of elements | H5: Guidelines
A6: Module + sub Module | B6: Functionality ( Sub Module) | C6: Elements (Refer Guidelines and Put here for reference) | D6: Low Complexity | E6: Medium compexity | F6: High Complexity | G6: Size | H6: Low Complexity | I6: Medium compexity | J6: High Complexity
D7: 1 | E7: 3 | F7: 5
A8: Asset Mapping - SQC/TPIA/Contractor | B8: SQC/TPIA/Contractor asset data and report on web; API integration and frontend fixes (Jun) | C8: US-AST-C5-001 - Asset Mapping - SQC/TPIA Contractor Data & Report on Web [M] US-AST-C5-002 - Asset Mapping - API Integration & Frontend Bug Fixes [M] Status: 2 Done | D8: 0 | E8: 2 | F8: 0 | G8: =D8*$D$7+E8*$E$7+F8*$F$7 -> 6
A9: Asset Mapping - Report Cleanup | B9: OHT Id cleanup in reports (Sep) | C9: US-SEP-19 - Dhara / Asset Mapping - Asset Mapping — OHT Id cleanup in reports [L] Status: 1 Open | D9: 1 | E9: 0 | F9: 0 | G9: =D9*$D$7+E9*$E$7+F9*$F$7 -> 1
A10: TOTAL ASSET MAPPING ESTIMATION (CYCLE 5) | G10: =SUM(G8:G9) -> 7
J11: Value added factors
B12: Total Count | G12: =G10 -> 7 | J12: Factor | L12: Rating
J13: Data Communications | L13: 0
B14: Productivity | C14: ='Baseline Productivity '!$C$4 -> 0.19 | J14: Distributed Data Processing | L14: 0
B15: Size | C15: =G10 -> 7 | D15: Point
B16: Effort | C16: =C15/C14 -> 36.842105 | D16: Man hours | J16: Performance | L16: 0
B17: VAF | C17: =0.65+0.01*$L$29 -> 1.01 | J17: Heavily used Configuration | L17: 3
B18: Risk contingency | C18: 0.05 | J18: Transaction Rate | L18: 4
B19: Project Management | C19: 0.1
B20: Total Planned effort | C20: =C16*C17*(1+C18+C19) -> 42.792105 | D20: Man hours | J20: Online Data Entry | L20: 3
J21: End-User Efficiency | L21: 2
B22: Permissible Range(Man hours) | C22: =C20*1.05 -> 44.931711 | D22: =C20*0.95 -> 40.6525 | J22: Online Update | L22: 1
J23: Complex Processing | L23: 3
J24: Reusability | L24: 4
J25: Installation Ease | L25: 4
J26: Operational Ease | L26: 4
J27: Multiple Sites | L27: 4
J28: Facilitate Change | L28: 4
J29: Total | L29: =SUM(L13:L28) -> 36

Sheet Bharosa CR Estimation
B1: Type Of work | C1: Development | D1: New Development
B2: Project Name | C2: Jal Rekha
B3: Remark | C3: Bharosa CR Module - Cycle 5 (Jun-Sep 2026)
D5: Volume/Count of elements | H5: Guidelines
A6: Module + sub Module | B6: Functionality ( Sub Module) | C6: Elements (Refer Guidelines and Put here for reference) | D6: Low Complexity | E6: Medium compexity | F6: High Complexity | G6: Size | H6: Low Complexity | I6: Medium compexity | J6: High Complexity
D7: 1 | E7: 3 | F7: 5
A8: Bharosa - Factory Testing | B8: Item master duplicate dropdown fix (web); factory testing mobile bug fixes (Jul) | C8: US-BHR-C5-001 - Bharosa - Item Master Duplicate Dropdown Entry Fix [L] US-BHR-C5-002 - Bharosa - Factory Testing Mobile Bug Fixes [M] Status: 2 Done | D8: 1 | E8: 1 | F8: 0 | G8: =D8*$D$7+E8*$E$7+F8*$F$7 -> 4
A9: Bharosa - Inspection Reassignment | B9: Inspection reassignment and photo-upload fix (Sep) | C9: US-SEP-23 - Bharosa - Bharosa inspection reassignment and photo-upload fix [L] Status: 1 In Progress | D9: 1 | E9: 0 | F9: 0 | G9: =D9*$D$7+E9*$E$7+F9*$F$7 -> 1
A10: TOTAL BHAROSA CR ESTIMATION (CYCLE 5) | G10: =SUM(G8:G9) -> 5
J11: Value added factors
B12: Total Count | G12: =G10 -> 5 | J12: Factor | L12: Rating
J13: Data Communications | L13: 0
B14: Productivity | C14: ='Baseline Productivity '!$C$4 -> 0.19 | J14: Distributed Data Processing | L14: 0
B15: Size | C15: =G10 -> 5 | D15: Point
B16: Effort | C16: =C15/C14 -> 26.315789 | D16: Man hours | J16: Performance | L16: 0
B17: VAF | C17: =0.65+0.01*$L$29 -> 1.01 | J17: Heavily used Configuration | L17: 3
B18: Risk contingency | C18: 0.05 | J18: Transaction Rate | L18: 4
B19: Project Management | C19: 0.1
B20: Total Planned effort | C20: =C16*C17*(1+C18+C19) -> 30.565789 | D20: Man hours | J20: Online Data Entry | L20: 3
J21: End-User Efficiency | L21: 2
B22: Permissible Range(Man hours) | C22: =C20*1.05 -> 32.094079 | D22: =C20*0.95 -> 29.0375 | J22: Online Update | L22: 1
J23: Complex Processing | L23: 3
J24: Reusability | L24: 4
J25: Installation Ease | L25: 4
J26: Operational Ease | L26: 4
J27: Multiple Sites | L27: 4
J28: Facilitate Change | L28: 4
J29: Total | L29: =SUM(L13:L28) -> 36

Sheet AI Module Estimation
B1: Type Of work | C1: Development | D1: New Development
B2: Project Name | C2: Jal Rekha
B3: Remark | C3: AI Module FHTC - Cycle 5 (Jun-Sep 2026)
D5: Volume/Count of elements | H5: Guidelines
A6: Module + sub Module | B6: Functionality ( Sub Module) | C6: Elements (Refer Guidelines and Put here for reference) | D6: Low Complexity | E6: Medium compexity | F6: High Complexity | G6: Size | H6: Low Complexity | I6: Medium compexity | J6: High Complexity
D7: 1 | E7: 3 | F7: 5
A8: AI Module - FHTC Tap Connection | B8: YOLO tap/person detection model, buffer-region validation, data processing and training pipeline (Jun) | C8: US-AI-C5-001 - AI Module - Tap & Person Detection Predictive Model [H] US-AI-C5-002 - AI Module - Tap Connection Buffer Region Validation (LLM/Pretrained Model Integration) [H] US-AI-C5-003 - AI Module - FHTC Data Processing & Model Training Pipeline [H] Status: 3 Done | D8: 0 | E8: 0 | F8: 3 | G8: =D8*$D$7+E8*$E$7+F8*$F$7 -> 15
A9: TOTAL AI MODULE ESTIMATION (CYCLE 5) | G9: =SUM(G8:G8) -> 15
J10: Value added factors
B11: Total Count | G11: =G9 -> 15 | J11: Factor | L11: Rating
J12: Data Communications | L12: 0
B13: Productivity | C13: ='Baseline Productivity '!$C$4 -> 0.19 | J13: Distributed Data Processing | L13: 0
B14: Size | C14: =G9 -> 15 | D14: Point
B15: Effort | C15: =C14/C13 -> 78.947368 | D15: Man hours | J15: Performance | L15: 0
B16: VAF | C16: =0.65+0.01*$L$28 -> 1.01 | J16: Heavily used Configuration | L16: 3
B17: Risk contingency | C17: 0.05 | J17: Transaction Rate | L17: 4
B18: Project Management | C18: 0.1
B19: Total Planned effort | C19: =C15*C16*(1+C17+C18) -> 91.697368 | D19: Man hours | J19: Online Data Entry | L19: 3
J20: End-User Efficiency | L20: 2
B21: Permissible Range(Man hours) | C21: =C19*1.05 -> 96.282237 | D21: =C19*0.95 -> 87.1125 | J21: Online Update | L21: 1
J22: Complex Processing | L22: 3
J23: Reusability | L23: 4
J24: Installation Ease | L24: 4
J25: Operational Ease | L25: 4
J26: Multiple Sites | L26: 4
J27: Facilitate Change | L27: 4
J28: Total | L28: =SUM(L12:L27) -> 36

Sheet CMMI Doc Estimation
B1: Type Of work | C1: Development | D1: New Development
B2: Project Name | C2: Jal Rekha
B3: Remark | C3: CMMI Documentation - Cycle 5 (Jun-Sep 2026)
D5: Volume/Count of elements | H5: Guidelines
A6: Module + sub Module | B6: Functionality ( Sub Module) | C6: Elements (Refer Guidelines and Put here for reference) | D6: Low Complexity | E6: Medium compexity | F6: High Complexity | G6: Size | H6: Low Complexity | I6: Medium compexity | J6: High Complexity
D7: 1 | E7: 3 | F7: 5
A8: CMMI Doc - Cycle 5 Data & Documentation | B8: Cycle 5 data collection; documentation streamlined for Cycle 5 modules (Jun-Jul) | C8: US-CMMI-C5-001 - CMMI Doc – Cycle 5 Data Collection (June 2026) [H] US-CMMI-C5-002 - CMMI Doc – Streamline Documentation for Cycle 5 Modules [H] Status: 2 In Progress | D8: 0 | E8: 0 | F8: 2 | G8: =D8*$D$7+E8*$E$7+F8*$F$7 -> 10
A9: CMMI Doc - Cycle 4 Closure | B9: Cycle 4 BRTM, release note, code review, SVN, Minitab analysis (Aug) | C9: US-AUG-29 - CMMI L5 - Cycle 4 BRTM and Release Note closure [H] Status: 1 In Progress | D9: 0 | E9: 0 | F9: 1 | G9: =D9*$D$7+E9*$E$7+F9*$F$7 -> 5
A10: TOTAL CMMI DOC ESTIMATION (CYCLE 5) | G10: =SUM(G8:G9) -> 15
J11: Value added factors
B12: Total Count | G12: =G10 -> 15 | J12: Factor | L12: Rating
J13: Data Communications | L13: 0
B14: Productivity | C14: ='Baseline Productivity '!$C$4 -> 0.19 | J14: Distributed Data Processing | L14: 0
B15: Size | C15: =G10 -> 15 | D15: Point
B16: Effort | C16: =C15/C14 -> 78.947368 | D16: Man hours | J16: Performance | L16: 0
B17: VAF | C17: =0.65+0.01*$L$29 -> 1.01 | J17: Heavily used Configuration | L17: 3
B18: Risk contingency | C18: 0.05 | J18: Transaction Rate | L18: 4
B19: Project Management | C19: 0.1
B20: Total Planned effort | C20: =C16*C17*(1+C18+C19) -> 91.697368 | D20: Man hours | J20: Online Data Entry | L20: 3
J21: End-User Efficiency | L21: 2
B22: Permissible Range(Man hours) | C22: =C20*1.05 -> 96.282237 | D22: =C20*0.95 -> 87.1125 | J22: Online Update | L22: 1
J23: Complex Processing | L23: 3
J24: Reusability | L24: 4
J25: Installation Ease | L25: 4
J26: Operational Ease | L26: 4
J27: Multiple Sites | L27: 4
J28: Facilitate Change | L28: 4
J29: Total | L29: =SUM(L13:L28) -> 36

Sheet e-Sign CDAC Estimation
B1: Type Of work | C1: Development | D1: New Development
B2: Project Name | C2: Jal Rekha
B3: Remark | C3: e-Sign via CDAC (Aadhaar) - Cycle 5 (Jun-Sep 2026)
D5: Volume/Count of elements | H5: Guidelines
A6: Module + sub Module | B6: Functionality ( Sub Module) | C6: Elements (Refer Guidelines and Put here for reference) | D6: Low Complexity | E6: Medium compexity | F6: High Complexity | G6: Size | H6: Low Complexity | I6: Medium compexity | J6: High Complexity
D7: 1 | E7: 3 | F7: 5
A8: e-Sign CDAC - FE & Contractor | B8: FE e-Sign on all logins; Contractor/Firm e-Sign for bill documents; O&M Contractor & GM e-Sign (Jun-Jul) | C8: US-ESIGN-C5-001 - e-Sign CDAC – FE e-Sign via Mobile/Web (All Logins) [H] US-ESIGN-C5-002 - e-Sign CDAC – Contractor/Firm e-Sign for O&M Bill Documents [H] US-OM-C5-010 - O&M Billing Workflow – e-Sign via CDAC (Contractor & GM) [H] Status: 3 In Progress | D8: 0 | E8: 0 | F8: 3 | G8: =D8*$D$7+E8*$E$7+F8*$F$7 -> 15
A9: e-Sign CDAC - TL Recommendation | B9: TL (PMC) recommendation letter via E-Office; TL (SQC)/TL (PMC) account office integration (Jul) | C9: US-ESIGN-C5-003 - e-Sign CDAC – TL (PMC) Recommendation Letter (E-Office Generated) [M] US-ESIGN-C5-004 - e-Sign CDAC – TL (SQC) & TL (PMC) Account Office Jal Rekha Integration [M] Status: 2 In Progress | D9: 0 | E9: 2 | F9: 0 | G9: =D9*$D$7+E9*$E$7+F9*$F$7 -> 6
A10: TOTAL E-SIGN CDAC ESTIMATION (CYCLE 5) | G10: =SUM(G8:G9) -> 21
J11: Value added factors
B12: Total Count | G12: =G10 -> 21 | J12: Factor | L12: Rating
J13: Data Communications | L13: 0
B14: Productivity | C14: ='Baseline Productivity '!$C$4 -> 0.19 | J14: Distributed Data Processing | L14: 0
B15: Size | C15: =G10 -> 21 | D15: Point
B16: Effort | C16: =C15/C14 -> 110.52632 | D16: Man hours | J16: Performance | L16: 0
B17: VAF | C17: =0.65+0.01*$L$29 -> 1.01 | J17: Heavily used Configuration | L17: 3
B18: Risk contingency | C18: 0.05 | J18: Transaction Rate | L18: 4
B19: Project Management | C19: 0.1
B20: Total Planned effort | C20: =C16*C17*(1+C18+C19) -> 128.37632 | D20: Man hours | J20: Online Data Entry | L20: 3
J21: End-User Efficiency | L21: 2
B22: Permissible Range(Man hours) | C22: =C20*1.05 -> 134.79513 | D22: =C20*0.95 -> 121.9575 | J22: Online Update | L22: 1
J23: Complex Processing | L23: 3
J24: Reusability | L24: 4
J25: Installation Ease | L25: 4
J26: Operational Ease | L26: 4
J27: Multiple Sites | L27: 4
J28: Facilitate Change | L28: 4
J29: Total | L29: =SUM(L13:L28) -> 36

Sheet BISAC-BISAG Estimation
B1: Type Of work | C1: Development | D1: New Development
B2: Project Name | C2: Jal Rekha
B3: Remark | C3: BISAC / BISAG Integration - Cycle 5 (Jun-Sep 2026)
D5: Volume/Count of elements | H5: Guidelines
A6: Module + sub Module | B6: Functionality ( Sub Module) | C6: Elements (Refer Guidelines and Put here for reference) | D6: Low Complexity | E6: Medium compexity | F6: High Complexity | G6: Size | H6: Low Complexity | I6: Medium compexity | J6: High Complexity
D7: 1 | E7: 3 | F7: 5
A8: BISAC - NIC Asset & Pipeline Mapping | B8: NIC Asset ID mapping, pipeline mapping with BISAC junction data, village LGD code logic (Jun-Jul) | C8: US-BISAC-C5-001 - BISAC – NIC Asset ID Mapping (Asset & Junction Mapping) [H] US-BISAC-C5-002 - BISAC – Pipeline Mapping with BISAC Junction Data [H] US-BISAC-C5-003 - BISAC – Village LGD Code Integration (Village without LGD = Habitation) [M] Status: 2 In Progress, 1 Done | D8: 0 | E8: 1 | F8: 2 | G8: =D8*$D$7+E8*$E$7+F8*$F$7 -> 13
A9: BISAG - Delhi Data Integration | B9: Asset & pipeline APIs, Annexure-C, shapefile API; scheme mapping and progress-reporting fix (Aug) | C9: US-AUG-31 - BISAG / Delhi Data Integration - Asset & Pipeline API and Annexure-C data sharing [H] US-AUG-32 - BISAG / Delhi Data Integration - Scheme mapping and progress-reporting fix [M] Status: 2 In Progress | D9: 0 | E9: 1 | F9: 1 | G9: =D9*$D$7+E9*$E$7+F9*$F$7 -> 8
A10: TOTAL BISAC-BISAG ESTIMATION (CYCLE 5) | G10: =SUM(G8:G9) -> 21
J11: Value added factors
B12: Total Count | G12: =G10 -> 21 | J12: Factor | L12: Rating
J13: Data Communications | L13: 0
B14: Productivity | C14: ='Baseline Productivity '!$C$4 -> 0.19 | J14: Distributed Data Processing | L14: 0
B15: Size | C15: =G10 -> 21 | D15: Point
B16: Effort | C16: =C15/C14 -> 110.52632 | D16: Man hours | J16: Performance | L16: 0
B17: VAF | C17: =0.65+0.01*$L$29 -> 1.01 | J17: Heavily used Configuration | L17: 3
B18: Risk contingency | C18: 0.05 | J18: Transaction Rate | L18: 4
B19: Project Management | C19: 0.1
B20: Total Planned effort | C20: =C16*C17*(1+C18+C19) -> 128.37632 | D20: Man hours | J20: Online Data Entry | L20: 3
J21: End-User Efficiency | L21: 2
B22: Permissible Range(Man hours) | C22: =C20*1.05 -> 134.79513 | D22: =C20*0.95 -> 121.9575 | J22: Online Update | L22: 1
J23: Complex Processing | L23: 3
J24: Reusability | L24: 4
J25: Installation Ease | L25: 4
J26: Operational Ease | L26: 4
J27: Multiple Sites | L27: 4
J28: Facilitate Change | L28: 4
J29: Total | L29: =SUM(L13:L28) -> 36

Sheet Other Modules Estimation
B1: Type Of work | C1: Development | D1: New Development
B2: Project Name | C2: Jal Rekha
B3: Remark | C3: Other Modules (Daily Inspection, Sopan, QA, Mobile, Dashboard, Admin, Jal Samadhan, Security) - Cycle 5 (Jun-Sep 2026)
D5: Volume/Count of elements | H5: Guidelines
A6: Module + sub Module | B6: Functionality ( Sub Module) | C6: Elements (Refer Guidelines and Put here for reference) | D6: Low Complexity | E6: Medium compexity | F6: High Complexity | G6: Size | H6: Low Complexity | I6: Medium compexity | J6: High Complexity
D7: 1 | E7: 3 | F7: 5
A8: Daily Inspection | B8: Role-based report modifications; mobile app bug fixes (Jun) | C8: US-DIN-C5-001 - Daily Inspection - Role-Based Report Modifications [M] US-DIN-C5-002 - Daily Inspection - Mobile App Bug Fixes [L] Status: 2 Done | D8: 1 | E8: 1 | F8: 0 | G8: =D8*$D$7+E8*$E$7+F8*$F$7 -> 4
A9: Sopan - Contractor Calendar | B9: Calendar functionality for 2026-27 on Contractor login, web and mobile (Jul) | C9: US-SOP-C5-001 - Sopan - Calendar Functionality for 2026-27 [M] Status: 1 Open | D9: 0 | E9: 1 | F9: 0 | G9: =D9*$D$7+E9*$E$7+F9*$F$7 -> 3
A10: QA / User & Role Management Automation | B10: Selenium (TestNG) scripts, automation review process, script extended through Assign Work (Jun, Sep) | C10: US-QA-C5-001 - QA Automation - Selenium Scripts for User Login & Registration [M] US-QA-C5-002 - QA Automation - Internal Review Process for Automation Testing [L] PSR-SEP-04 - User & Role Management - Selenium automation extended through Assign Work [M] Status: 3 Done | D10: 1 | E10: 2 | F10: 0 | G10: =D10*$D$7+E10*$E$7+F10*$F$7 -> 7
A11: Mobile App - Fixes & Stability | B11: UI/functional bug fixes (Aug); Play Console crash/ANR fixes (Sep); Azure DevOps Android CI/CD pipeline (Jun) | C11: US-AUG-28 - Mobile App - Mobile app UI/functional bug fixes [M] US-SEP-37 - Mobile App Stability - Crash and ANR fixes from Play Console vitals [H] PSR-JUN-01 - CI/CD - Azure DevOps Android pipeline implementation [M] Status: 2 Done, 1 Open | D11: 0 | E11: 2 | F11: 1 | G11: =D11*$D$7+E11*$E$7+F11*$F$7 -> 11
A12: Dashboard & Public Reports | B12: Redesign of all module inner pages, public reports on dashboard (Jul); login and forgot-password page UI (Sep) | C12: PSR-JUL-01 - Dashboard - redesign of all module and inner pages of Jal Rekha [M] PSR-JUL-02 - All public reports on dashboard - sanity testing, bug fixes, report preparation [H] PSR-SEP-01 - Dashboard - login page and forgot-password page UI fixes [M] Status: 3 Done | D12: 0 | E12: 2 | F12: 1 | G12: =D12*$D$7+E12*$E$7+F12*$F$7 -> 11
A13: Admin / ID Management | B13: PIU district-wise restructuring and TL-ID/PIU-ID linking (Aug) | C13: US-AUG-36 - Admin / ID Management - PIU district-wise restructuring and TL-ID/PIU-ID linking [H] Status: 1 Not Started | D13: 0 | E13: 0 | F13: 1 | G13: =D13*$D$7+E13*$E$7+F13*$F$7 -> 5
A14: Jal Samadhan | B14: Complaint queries module with SLA escalation (Aug); CM Helpline 181 integration (Sep) | C14: US-AUG-37 - Jal Samadhan - Complaint Queries module [M] US-SEP-35 - Jal Samadhan - CM Helpline (181) integration for Jal Samadhan [H] Status: 1 Not Started, 1 Open | D14: 0 | E14: 1 | F14: 1 | G14: =D14*$D$7+E14*$E$7+F14*$F$7 -> 8
A15: Security - Two-Factor Authentication | B15: 2FA implementation for GM login IDs (Sep) | C15: US-SEP-36 - Jal Rekha — Security (2FA) - Two-Factor Authentication — current scope confirmed [H] Status: 1 Done | D15: 0 | E15: 0 | F15: 1 | G15: =D15*$D$7+E15*$E$7+F15*$F$7 -> 5
A16: TOTAL OTHER MODULES ESTIMATION (CYCLE 5) | G16: =SUM(G8:G15) -> 54
J17: Value added factors
B18: Total Count | G18: =G16 -> 54 | J18: Factor | L18: Rating
J19: Data Communications | L19: 0
B20: Productivity | C20: ='Baseline Productivity '!$C$4 -> 0.19 | J20: Distributed Data Processing | L20: 0
B21: Size | C21: =G16 -> 54 | D21: Point
B22: Effort | C22: =C21/C20 -> 284.21053 | D22: Man hours | J22: Performance | L22: 0
B23: VAF | C23: =0.65+0.01*$L$35 -> 1.01 | J23: Heavily used Configuration | L23: 3
B24: Risk contingency | C24: 0.05 | J24: Transaction Rate | L24: 4
B25: Project Management | C25: 0.1
B26: Total Planned effort | C26: =C22*C23*(1+C24+C25) -> 330.11053 | D26: Man hours | J26: Online Data Entry | L26: 3
J27: End-User Efficiency | L27: 2
B28: Permissible Range(Man hours) | C28: =C26*1.05 -> 346.61605 | D28: =C26*0.95 -> 313.605 | J28: Online Update | L28: 1
J29: Complex Processing | L29: 3
J30: Reusability | L30: 4
J31: Installation Ease | L31: 4
J32: Operational Ease | L32: 4
J33: Multiple Sites | L33: 4
J34: Facilitate Change | L34: 4
J35: Total | L35: =SUM(L19:L34) -> 36

Sheet Story Mapping
A1: Jal Rekha - Cycle 5 (Jun-Sep 2026) Estimation: Story-to-Size Mapping (audit trail)
A2: Complexity rule: weights Low=1, Medium=3, High=5 (as per Master / Guidelines sheets).
A3: Jun-Jul stories (Consolidated Register): source effort <=6 hrs = Low, 7-19 hrs = Medium, >=20 hrs = High.
A4: Aug-Sep stories (Sprint 19/20 documents carry no hours): acceptance-criteria count <=3 Low, 4-5 Medium, >=6 High; +1 level for external-system integration, multi-role workflow, KPI dashboards or complex multi-store business rules; -1 level for pure fix/rename/display scope. Overrides are stated in the Basis column.
A5: PSR/timesheet-only items (no user story): level from timesheet hours with the same hours rule.
A6: Excluded: duplicates of already-sized scope, confirmation-only stories, Cycle 4 scope and non-development activity (reason shown). The 41 stories in the Cycle 5 / CR Backlog document (US-C5-xx, US-CR-xx) restate register scope per the register CR Cross-Reference and are not counted again.
A8: Sr. | B8: Story ID | C8: Source | D8: Module / Title | E8: Status | F8: Period | G8: Counted | H8: Estimation Sheet | I8: Sub-module Row | J8: ACs | K8: Source Effort (hrs) | L8: Complexity | M8: Points | N8: Basis / Reason
A9: 1 | B9: US-OM-C5-001 | C9: Consolidated Register (Jun-Jul 2026) | D9: O&M Billing – Abstract Report Generation | E9: Done | F9: Jun 2026 | G9: Yes | H9: O&M Estimation | I9: O&M Billing - Abstract, Bill PDF & Review | J9: 6 | K9: 20 | L9: High | M9: =IF(L9="Low",1,IF(L9="Medium",3,IF(L9="High",5,0))) -> 5 | N9: Source effort 20 hrs: <=6 Low, 7-19 Medium, >=20 High
A10: 2 | B10: US-OM-C5-002 | C10: Consolidated Register (Jun-Jul 2026) | D10: O&M Billing – Contractor Mistake Correction by SQC/TL → GM | E10: Done | F10: Jun 2026 | G10: Yes | H10: O&M Estimation | I10: O&M Billing - Abstract, Bill PDF & Review | J10: 5 | K10: 16 | L10: Medium | M10: =IF(L10="Low",1,IF(L10="Medium",3,IF(L10="High",5,0))) -> 3 | N10: Source effort 16 hrs: <=6 Low, 7-19 Medium, >=20 High
A11: 3 | B11: US-OM-C5-003 | C11: Consolidated Register (Jun-Jul 2026) | D11: O&M Billing – Show All Records on All IDs (GM, SQC) | E11: Done | F11: Jun 2026 | G11: Yes | H11: O&M Estimation | I11: O&M Billing - Abstract, Bill PDF & Review | J11: 6 | K11: 8 | L11: Medium | M11: =IF(L11="Low",1,IF(L11="Medium",3,IF(L11="High",5,0))) -> 3 | N11: Source effort 8 hrs: <=6 Low, 7-19 Medium, >=20 High
A12: 4 | B12: US-OM-C5-004 | C12: Consolidated Register (Jun-Jul 2026) | D12: O&M Billing – Merge PDF of All O&M Bill Documents | E12: Done | F12: Jun 2026 | G12: Yes | H12: O&M Estimation | I12: O&M Billing - Abstract, Bill PDF & Review | J12: 5 | K12: 16 | L12: Medium | M12: =IF(L12="Low",1,IF(L12="Medium",3,IF(L12="High",5,0))) -> 3 | N12: Source effort 16 hrs: <=6 Low, 7-19 Medium, >=20 High
A13: 5 | B13: US-OM-C5-005 | C13: Consolidated Register (Jun-Jul 2026) | D13: O&M Billing – Power Consumption: Contractor & GM Side Changes | E13: In Progress | F13: Jun-Jul 2026 | G13: Yes | H13: O&M Estimation | I13: O&M Billing - Power, Construction Bill & Complaints | J13: 5 | K13: 24 | L13: High | M13: =IF(L13="Low",1,IF(L13="Medium",3,IF(L13="High",5,0))) -> 5 | N13: Source effort 24 hrs: <=6 Low, 7-19 Medium, >=20 High
A14: 6 | B14: US-OM-C5-006 | C14: Consolidated Register (Jun-Jul 2026) | D14: O&M Billing – Two New Columns in Water Supply During Construction Bill | E14: In Progress | F14: Jun 2026 | G14: Yes | H14: O&M Estimation | I14: O&M Billing - Power, Construction Bill & Complaints | J14: 5 | K14: 8 | L14: Medium | M14: =IF(L14="Low",1,IF(L14="Medium",3,IF(L14="High",5,0))) -> 3 | N14: Source effort 8 hrs: <=6 Low, 7-19 Medium, >=20 High
A15: 7 | B15: US-OM-C5-007 | C15: Consolidated Register (Jun-Jul 2026) | D15: O&M Billing – O&M Villages: Construction Approval Status | E15: In Progress | F15: Jul 2026 | G15: Yes | H15: O&M Estimation | I15: O&M Billing - Power, Construction Bill & Complaints | J15: 5 | K15: 8 | L15: Medium | M15: =IF(L15="Low",1,IF(L15="Medium",3,IF(L15="High",5,0))) -> 3 | N15: Source effort 8 hrs: <=6 Low, 7-19 Medium, >=20 High
A16: 8 | B16: US-OM-C5-008 | C16: Consolidated Register (Jun-Jul 2026) | D16: O&M Billing – Aaklan Contractor Dispute: Dhara Data Discrepancy Window | E16: In Progress | F16: Jul 2026 | G16: Yes | H16: O&M Estimation | I16: O&M Billing - Dispute, LGD & GST | J16: 5 | K16: 16 | L16: Medium | M16: =IF(L16="Low",1,IF(L16="Medium",3,IF(L16="High",5,0))) -> 3 | N16: Source effort 16 hrs: <=6 Low, 7-19 Medium, >=20 High
A17: 9 | B17: US-OM-C5-009 | C17: Consolidated Register (Jun-Jul 2026) | D17: O&M Billing – GM: Pump Transformer 10% Deduction Logic | E17: In Progress | F17: Jul 2026 | G17: Yes | H17: O&M Estimation | I17: O&M Billing - Power, Construction Bill & Complaints | J17: 5 | K17: 8 | L17: Medium | M17: =IF(L17="Low",1,IF(L17="Medium",3,IF(L17="High",5,0))) -> 3 | N17: Source effort 8 hrs: <=6 Low, 7-19 Medium, >=20 High
A18: 10 | B18: US-OM-C5-010 | C18: Consolidated Register (Jun-Jul 2026) | D18: O&M Billing Workflow – e-Sign via CDAC (Contractor & GM) | E18: In Progress | F18: Jun-Jul 2026 | G18: Yes | H18: e-Sign CDAC Estimation | I18: e-Sign CDAC - FE & Contractor | J18: 6 | K18: 40 | L18: High | M18: =IF(L18="Low",1,IF(L18="Medium",3,IF(L18="High",5,0))) -> 5 | N18: Source effort 40 hrs: <=6 Low, 7-19 Medium, >=20 High
A19: 11 | B19: US-OM-C5-011 | C19: Consolidated Register (Jun-Jul 2026) | D19: O&M Billing – GM (PIU) Login: Bill PDF (19–20 Docs) & 3-Month Consolidation | E19: Done | F19: Jun 2026 | G19: Yes | H19: O&M Estimation | I19: O&M Billing - Abstract, Bill PDF & Review | J19: 5 | K19: 12 | L19: Medium | M19: =IF(L19="Low",1,IF(L19="Medium",3,IF(L19="High",5,0))) -> 3 | N19: Source effort 12 hrs: <=6 Low, 7-19 Medium, >=20 High
A20: 12 | B20: US-OM-C5-012 | C20: Consolidated Register (Jun-Jul 2026) | D20: O&M Billing – Sahbhagita Generate Abstract: Select RA Bill & Tag All | E20: Done | F20: Jun 2026 | G20: Yes | H20: O&M Estimation | I20: O&M Billing - Abstract, Bill PDF & Review | J20: 5 | K20: 8 | L20: Medium | M20: =IF(L20="Low",1,IF(L20="Medium",3,IF(L20="High",5,0))) -> 3 | N20: Source effort 8 hrs: <=6 Low, 7-19 Medium, >=20 High
... A73: 65 | B73: US-SVS-C5-004 | C73: Consolidated Register (Jun-Jul 2026) | D73: SVS – Remove JJM ID and Village Status Fields | E73: Done | F73: Jun 2026 | G73: Yes | H73: SVS Estimation | I73: SVS - Daily Water Supply Entry | J73: 5 | K73: 4 | L73: Low | M73: =IF(L73="Low",1,IF(L73="Medium",3,IF(L73="High",5,0))) -> 1 | N73: Source effort 4 hrs: <=6 Low, 7-19 Medium, >=20 High
A74: 66 | B74: US-VST-OTP-C5-001 | C74: Consolidated Register (Jun-Jul 2026) | D74: Vistrit – OTP Verification on Scheme/OHT/Bulk Master (GM Edit/Delete) | E74: Done | F74: Jun 2026 | G74: No | J74: 5 | K74: 8 | M74: =IF(L74="Low",1,IF(L74="Medium",3,IF(L74="High",5,0))) -> 0 | N74: Excluded: Duplicate of US-VST-C5-002 (OTP on GM edit/delete)
A75: 67 | B75: US-VST-OTP-C5-002 | C75: Consolidated Register (Jun-Jul 2026) | D75: Vistrit – Scheme Village Mapping: Duplicate Village Validation | E75: Done | F75: Jun 2026 | G75: Yes | H75: Master Estimation | I75: Vistrit - Mapping, OTP & Validation | J75: 5 | K75: 4 | L75: Low | M75: =IF(L75="Low",1,IF(L75="Medium",3,IF(L75="High",5,0))) -> 1 | N75: Source effort 4 hrs: <=6 Low, 7-19 Medium, >=20 High
A76: 68 | B76: US-CMMI-C5-001 | C76: Consolidated Register (Jun-Jul 2026) | D76: CMMI Doc – Cycle 5 Data Collection (June 2026) | E76: In Progress | F76: Jun-Jul 2026 | G76: Yes | H76: CMMI Doc Estimation | I76: CMMI Doc - Cycle 5 Data & Documentation | J76: 5 | K76: 40 | L76: High | M76: =IF(L76="Low",1,IF(L76="Medium",3,IF(L76="High",5,0))) -> 5 | N76: Source effort 40 hrs: <=6 Low, 7-19 Medium, >=20 High
A77: 69 | B77: US-CMMI-C5-002 | C77: Consolidated Register (Jun-Jul 2026) | D77: CMMI Doc – Streamline Documentation for Cycle 5 Modules | E77: In Progress | F77: Jun-Jul 2026 | G77: Yes | H77: CMMI Doc Estimation | I77: CMMI Doc - Cycle 5 Data & Documentation | J77: 5 | K77: 60 | L77: High | M77: =IF(L77="Low",1,IF(L77="Medium",3,IF(L77="High",5,0))) -> 5 | N77: Source effort 60 hrs: <=6 Low, 7-19 Medium, >=20 High
A78: 70 | B78: US-OMWF-C4-001 | C78: Consolidated Register (Jun-Jul 2026) | D78: O&M Billing Workflow – Firm Bill Submission | E78: Done | F78: Cycle 4 | G78: No | J78: 6 | M78: =IF(L78="Low",1,IF(L78="Medium",3,IF(L78="High",5,0))) -> 0 | N78: Excluded: Cycle 4 scope (Sprint 12-16, delivered Jan-May 2026) - already estimated in Cycle 4 O&M Billing Workflow row
A79: 71 | B79: US-OMWF-C4-002 | C79: Consolidated Register (Jun-Jul 2026) | D79: O&M Billing Workflow – GM (PIU) Forward to TL (CSC) | E79: Done | F79: Cycle 4 | G79: No | J79: 5 | M79: =IF(L79="Low",1,IF(L79="Medium",3,IF(L79="High",5,0))) -> 0 | N79: Excluded: Cycle 4 scope (Sprint 12-16, delivered Jan-May 2026) - already estimated in Cycle 4 O&M Billing Workflow row
A80: 72 | B80: US-OMWF-C4-003 | C80: Consolidated Register (Jun-Jul 2026) | D80: O&M Billing Workflow – TL (CSC) Review & Recommendation | E80: Done | F80: Cycle 4 | G80: No | J80: 5 | M80: =IF(L80="Low",1,IF(L80="Medium",3,IF(L80="High",5,0))) -> 0 | N80: Excluded: Cycle 4 scope (Sprint 12-16, delivered Jan-May 2026) - already estimated in Cycle 4 O&M Billing Workflow row
A81: 73 | B81: US-OMWF-C4-004 | C81: Consolidated Register (Jun-Jul 2026) | D81: O&M Billing Workflow – GM (PIU) Final Data Entry & Signed Document Upload | E81: Done | F81: Cycle 4 | G81: No | J81: 6 | M81: =IF(L81="Low",1,IF(L81="Medium",3,IF(L81="High",5,0))) -> 0 | N81: Excluded: Cycle 4 scope (Sprint 12-16, delivered Jan-May 2026) - already estimated in Cycle 4 O&M Billing Workflow row
A82: 74 | B82: US-OMWF-C4-005 | C82: Consolidated Register (Jun-Jul 2026) | D82: O&M Billing Workflow – GM (O&M) to TL (PMC) Routing | E82: Done | F82: Cycle 4 | G82: No | J82: 5 | M82: =IF(L82="Low",1,IF(L82="Medium",3,IF(L82="High",5,0))) -> 0 | N82: Excluded: Cycle 4 scope (Sprint 12-16, delivered Jan-May 2026) - already estimated in Cycle 4 O&M Billing Workflow row
A83: 75 | B83: US-OMWF-C4-006 | C83: Consolidated Register (Jun-Jul 2026) | D83: O&M Billing Workflow – DGM (O&M) Review | E83: Done | F83: Cycle 4 | G83: No | J83: 5 | M83: =IF(L83="Low",1,IF(L83="Medium",3,IF(L83="High",5,0))) -> 0 | N83: Excluded: Cycle 4 scope (Sprint 12-16, delivered Jan-May 2026) - already estimated in Cycle 4 O&M Billing Workflow row
A84: 76 | B84: US-OMWF-C4-007 | C84: Consolidated Register (Jun-Jul 2026) | D84: O&M Billing Workflow – GM (O&M) Pass Order & HO Letter Upload | E84: Done | F84: Cycle 4 | G84: No | J84: 5 | M84: =IF(L84="Low",1,IF(L84="Medium",3,IF(L84="High",5,0))) -> 0 | N84: Excluded: Cycle 4 scope (Sprint 12-16, delivered Jan-May 2026) - already estimated in Cycle 4 O&M Billing Workflow row
A85: 77 | B85: US-OMWF-C4-008 | C85: Consolidated Register (Jun-Jul 2026) | D85: O&M Billing Workflow – CGM Regional Office Routing | E85: Done | F85: Cycle 4 | G85: No | J85: 5 | M85: =IF(L85="Low",1,IF(L85="Medium",3,IF(L85="High",5,0))) -> 0 | N85: Excluded: Cycle 4 scope (Sprint 12-16, delivered Jan-May 2026) - already estimated in Cycle 4 O&M Billing Workflow row
A86: 78 | B86: US-OMWF-C4-009 | C86: Consolidated Register (Jun-Jul 2026) | D86: O&M Billing Workflow – CA Financial Review | E86: Done | F86: Cycle 4 | G86: No | J86: 5 | M86: =IF(L86="Low",1,IF(L86="Medium",3,IF(L86="High",5,0))) -> 0 | N86: Excluded: Cycle 4 scope (Sprint 12-16, delivered Jan-May 2026) - already estimated in Cycle 4 O&M Billing Workflow row
A87: 79 | B87: US-OMWF-C4-010 | C87: Consolidated Register (Jun-Jul 2026) | D87: O&M Billing Workflow – CFO Sign-off | E87: Done | F87: Cycle 4 | G87: No | J87: 5 | M87: =IF(L87="Low",1,IF(L87="Medium",3,IF(L87="High",5,0))) -> 0 | N87: Excluded: Cycle 4 scope (Sprint 12-16, delivered Jan-May 2026) - already estimated in Cycle 4 O&M Billing Workflow row
A88: 80 | B88: US-OMWF-C4-011 | C88: Consolidated Register (Jun-Jul 2026) | D88: O&M Billing Workflow – P.D. Review | E88: Done | F88: Cycle 4 | G88: No | J88: 5 | M88: =IF(L88="Low",1,IF(L88="Medium",3,IF(L88="High",5,0))) -> 0 | N88: Excluded: Cycle 4 scope (Sprint 12-16, delivered Jan-May 2026) - already estimated in Cycle 4 O&M Billing Workflow row
A89: 81 | B89: US-OMWF-C4-012 | C89: Consolidated Register (Jun-Jul 2026) | D89: O&M Billing Workflow – MD Final Approval | E89: Done | F89: Cycle 4 | G89: No | J89: 5 | M89: =IF(L89="Low",1,IF(L89="Medium",3,IF(L89="High",5,0))) -> 0 | N89: Excluded: Cycle 4 scope (Sprint 12-16, delivered Jan-May 2026) - already estimated in Cycle 4 O&M Billing Workflow row
... A93: 85 | B93: US-OMWF-C4-016 | C93: Consolidated Register (Jun-Jul 2026) | D93: O&M Billing Workflow – End-to-End Workflow Testing | E93: WIP | F93: Cycle 4 | G93: No | J93: 6 | M93: =IF(L93="Low",1,IF(L93="Medium",3,IF(L93="High",5,0))) -> 0 | N93: Excluded: Cycle 4 scope (Sprint 12-16, delivered Jan-May 2026) - already estimated in Cycle 4 O&M Billing Workflow row
A94: 86 | B94: US-MAT-C5-001 | C94: Consolidated Register (Jun-Jul 2026) | D94: Material Testing - Re-Inspection Loop (2nd Loop after GM Rejection) | E94: In Progress | F94: Jul 2026 | G94: Yes | H94: Material Testing Estimation | I94: Material Testing - Re-Inspection Loop | J94: 5 | K94: 16 | L94: Medium | M94: =IF(L94="Low",1,IF(L94="Medium",3,IF(L94="High",5,0))) -> 3 | N94: Source effort 16 hrs: <=6 Low, 7-19 Medium, >=20 High
A95: 87 | B95: US-MAT-C5-002 | C95: Consolidated Register (Jun-Jul 2026) | D95: Material Testing - Optional Image Upload on Second RFI Loop | E95: Open | F95: Jul 2026 | G95: Yes | H95: Material Testing Estimation | I95: Material Testing - Re-Inspection Loop | J95: 4 | K95: 6 | L95: Low | M95: =IF(L95="Low",1,IF(L95="Medium",3,IF(L95="High",5,0))) -> 1 | N95: Source effort 6 hrs: <=6 Low, 7-19 Medium, >=20 High
A96: 88 | B96: US-MAT-C5-003 | C96: Consolidated Register (Jun-Jul 2026) | D96: Material Testing - GM/Contractor Login Database & API Enhancements | E96: In Progress | F96: Jul 2026 | G96: Yes | H96: Material Testing Estimation | I96: Material Testing - GM/Contractor DB & API | J96: 4 | K96: 20 | L96: High | M96: =IF(L96="Low",1,IF(L96="Medium",3,IF(L96="High",5,0))) -> 5 | N96: Source effort 20 hrs: <=6 Low, 7-19 Medium, >=20 High
A97: 89 | B97: US-NRM-C5-001 | C97: Consolidated Register (Jun-Jul 2026) | D97: Nirmal - Beneficiary Report Issue Fix | E97: Done | F97: Jun 2026 | G97: Yes | H97: Nirmal Estimation | I97: Nirmal - Reports & Bug Fixes | J97: 4 | K97: 8 | L97: Medium | M97: =IF(L97="Low",1,IF(L97="Medium",3,IF(L97="High",5,0))) -> 3 | N97: Source effort 8 hrs: <=6 Low, 7-19 Medium, >=20 High
A98: 90 | B98: US-NRM-C5-002 | C98: Consolidated Register (Jun-Jul 2026) | D98: Nirmal - Contractor Login Report Counting Bug Fix | E98: Done | F98: Jun 2026 | G98: Yes | H98: Nirmal Estimation | I98: Nirmal - Reports & Bug Fixes | J98: 4 | K98: 6 | L98: Low | M98: =IF(L98="Low",1,IF(L98="Medium",3,IF(L98="High",5,0))) -> 1 | N98: Source effort 6 hrs: <=6 Low, 7-19 Medium, >=20 High
A99: 91 | B99: US-NRM-C5-003 | C99: Consolidated Register (Jun-Jul 2026) | D99: Nirmal - FE Mobile Reports Validation & Bug Fixes | E99: Done | F99: Jun 2026 | G99: Yes | H99: Nirmal Estimation | I99: Nirmal - Reports & Bug Fixes | J99: 4 | K99: 8 | L99: Medium | M99: =IF(L99="Low",1,IF(L99="Medium",3,IF(L99="High",5,0))) -> 3 | N99: Source effort 8 hrs: <=6 Low, 7-19 Medium, >=20 High
A100: 92 | B100: US-NRM-C5-004 | C100: Consolidated Register (Jun-Jul 2026) | D100: Nirmal - Test Scenario and Test Case Creation | E100: Done | F100: Jun 2026 | G100: Yes | H100: Nirmal Estimation | I100: Nirmal - Reports & Bug Fixes | J100: 4 | K100: 6 | L100: Low | M100: =IF(L100="Low",1,IF(L100="Medium",3,IF(L100="High",5,0))) -> 1 | N100: Source effort 6 hrs: <=6 Low, 7-19 Medium, >=20 High
A101: 93 | B101: US-AI-C5-001 | C101: Consolidated Register (Jun-Jul 2026) | D101: AI Module - Tap & Person Detection Predictive Model | E101: Done | F101: Jun 2026 | G101: Yes | H101: AI Module Estimation | I101: AI Module - FHTC Tap Connection | J101: 4 | K101: 40 | L101: High | M101: =IF(L101="Low",1,IF(L101="Medium",3,IF(L101="High",5,0))) -> 5 | N101: Source effort 40 hrs: <=6 Low, 7-19 Medium, >=20 High
A102: 94 | B102: US-AI-C5-002 | C102: Consolidated Register (Jun-Jul 2026) | D102: AI Module - Tap Connection Buffer Region Validation (LLM/Pretrained Model Integration) | E102: Done | F102: Jun 2026 | G102: Yes | H102: AI Module Estimation | I102: AI Module - FHTC Tap Connection | J102: 4 | K102: 32 | L102: High | M102: =IF(L102="Low",1,IF(L102="Medium",3,IF(L102="High",5,0))) -> 5 | N102: Source effort 32 hrs: <=6 Low, 7-19 Medium, >=20 High
A103: 95 | B103: US-AI-C5-003 | C103: Consolidated Register (Jun-Jul 2026) | D103: AI Module - FHTC Data Processing & Model Training Pipeline | E103: Done | F103: Jun 2026 | G103: Yes | H103: AI Module Estimation | I103: AI Module - FHTC Tap Connection | J103: 4 | K103: 32 | L103: High | M103: =IF(L103="Low",1,IF(L103="Medium",3,IF(L103="High",5,0))) -> 5 | N103: Source effort 32 hrs: <=6 Low, 7-19 Medium, >=20 High
A104: 96 | B104: US-MSTR-C5-001 | C104: Consolidated Register (Jun-Jul 2026) | D104: Master - Lock Scheme/Village/OHT Master Once Linked to Live Transactions | E104: Open | F104: Jul 2026 | G104: Yes | H104: Master Estimation | I104: Master - Lock & Data Integrity | J104: 4 | K104: 16 | L104: Medium | M104: =IF(L104="Low",1,IF(L104="Medium",3,IF(L104="High",5,0))) -> 3 | N104: Source effort 16 hrs: <=6 Low, 7-19 Medium, >=20 High
A105: 97 | B105: US-MSTR-C5-002 | C105: Consolidated Register (Jun-Jul 2026) | D105: Master - Dhara Mapped Summary Report Search Debugging & Enhancement | E105: Done | F105: Jun 2026 | G105: Yes | H105: Master Estimation | I105: Master - Lock & Data Integrity | J105: 4 | K105: 8 | L105: Medium | M105: =IF(L105="Low",1,IF(L105="Medium",3,IF(L105="High",5,0))) -> 3 | N105: Source effort 8 hrs: <=6 Low, 7-19 Medium, >=20 High
... A115: 107 | B115: US-QA-C5-002 | C115: Consolidated Register (Jun-Jul 2026) | D115: QA Automation - Internal Review Process for Automation Testing | E115: Done | F115: Jun-Jul 2026 | G115: Yes | H115: Other Modules Estimation | I115: QA / User & Role Management Automation | J115: 4 | K115: 4 | L115: Low | M115: =IF(L115="Low",1,IF(L115="Medium",3,IF(L115="High",5,0))) -> 1 | N115: Source effort 4 hrs: <=6 Low, 7-19 Medium, >=20 High
A116: 108 | B116: US-AUG-01 | C116: Sprint 19 User Stories (Aug 2026) | D116: O&M Billing — WSDCP - New WSDCP tab and Bill Generation status tracking | E116: In Progress | F116: Aug 2026 | G116: Yes | H116: O&M Estimation | I116: O&M Billing - WSDCP Phase 1 | J116: 5 | L116: High | M116: =IF(L116="Low",1,IF(L116="Medium",3,IF(L116="High",5,0))) -> 5 | N116: AC=5 (Medium) +1: new workflow-stage tracking and bill history across multiple data stores
A117: 109 | B117: US-AUG-02 | C117: Sprint 19 User Stories (Aug 2026) | D117: O&M Billing — WSDCP - WSDCP Payment Details tab | E117: In Progress | F117: Aug 2026 | G117: Yes | H117: O&M Estimation | I117: O&M Billing - WSDCP Phase 1 | J117: 7 | L117: High | M117: =IF(L117="Low",1,IF(L117="Medium",3,IF(L117="High",5,0))) -> 5 | N117: AC=7 (High): agreement fetch, variation orders, multi-field computation
A118: 110 | B118: US-AUG-03 | C118: Sprint 19 User Stories (Aug 2026) | D118: O&M Billing — WSDCP - WSDCP Power Consumption Sheet — Banked Units logic | E118: In Progress | F118: Aug 2026 | G118: Yes | H118: O&M Estimation | I118: O&M Billing - WSDCP Phase 1 | J118: 5 | L118: High | M118: =IF(L118="Low",1,IF(L118="Medium",3,IF(L118="High",5,0))) -> 5 | N118: AC=5 (Medium) +1: banked-units business rules validated against sample scheme formula
A119: 111 | B119: US-AUG-04 | C119: Sprint 19 User Stories (Aug 2026) | D119: O&M Billing — WSDCP - WSDCP Monthly Bill Sheet — Functional HSC and deductions | E119: In Progress | F119: Aug 2026 | G119: Yes | H119: O&M Estimation | I119: O&M Billing - WSDCP Phase 1 | J119: 6 | L119: High | M119: =IF(L119="Low",1,IF(L119="Medium",3,IF(L119="High",5,0))) -> 5 | N119: AC=6 (High): gross-amount formula, deductions table, net payable and GST
A120: 112 | B120: US-AUG-05 | C120: Sprint 19 User Stories (Aug 2026) | D120: O&M Billing — WSDCP - WSDCP UFW Report (no penalty) | E120: Done | F120: Aug 2026 | G120: Yes | H120: O&M Estimation | I120: O&M Billing - WSDCP Phase 1 | J120: 3 | L120: Low | M120: =IF(L120="Low",1,IF(L120="Medium",3,IF(L120="High",5,0))) -> 1 | N120: AC=3 (Low): report display, no penalty logic
A121: 113 | B121: US-AUG-06 | C121: Sprint 19 User Stories (Aug 2026) | D121: O&M Billing — WSDCP - WSDCP User Acceptance Testing on pilot scheme | E121: In Progress | F121: Aug 2026 | G121: Yes | H121: O&M Estimation | I121: O&M Billing - WSDCP Phase 1 | J121: 4 | L121: Medium | M121: =IF(L121="Low",1,IF(L121="Medium",3,IF(L121="High",5,0))) -> 3 | N121: AC=4 (Medium): UAT across four screen sets on one pilot scheme
A122: 114 | B122: US-AUG-07 | C122: Sprint 19 User Stories (Aug 2026) | D122: O&M Billing — Workflow - Full multi-role forward/backward billing workflow | E122: In Progress | F122: Aug 2026 | G122: Yes | H122: O&M Estimation | I122: O&M Billing - Multi-role Workflow | J122: 5 | L122: High | M122: =IF(L122="Low",1,IF(L122="Medium",3,IF(L122="High",5,0))) -> 5 | N122: AC=5 (Medium) +1: multi-role forward/backward routing
A123: 115 | B123: US-AUG-08 | C123: Sprint 19 User Stories (Aug 2026) | D123: O&M Billing — Workflow - GM/SQC edit rights on bill data with mandatory remark | E123: In Progress | F123: Aug 2026 | G123: Yes | H123: O&M Estimation | I123: O&M Billing - Multi-role Workflow | J123: 6 | L123: High | M123: =IF(L123="Low",1,IF(L123="Medium",3,IF(L123="High",5,0))) -> 5 | N123: AC=6 (High): edit rights with mandatory remark across four sheets
A124: 116 | B124: US-AUG-09 | C124: Sprint 19 User Stories (Aug 2026) | D124: O&M Billing — Workflow - SQC-not-available fallback — GM confirms directly | E124: In Progress | F124: Aug 2026 | G124: Yes | H124: O&M Estimation | I124: O&M Billing - Multi-role Workflow | J124: 5 | L124: Medium | M124: =IF(L124="Low",1,IF(L124="Medium",3,IF(L124="High",5,0))) -> 3 | N124: AC=5 (Medium): single-SQC fallback routing
A125: 117 | B125: US-AUG-10 | C125: Sprint 19 User Stories (Aug 2026) | D125: O&M Billing — Workflow - Higher Officials approval chain (GM O&M → MD) | E125: In Progress | F125: Aug 2026 | G125: Yes | H125: O&M Estimation | I125: O&M Billing - Multi-role Workflow | J125: 5 | L125: High | M125: =IF(L125="Low",1,IF(L125="Medium",3,IF(L125="High",5,0))) -> 5 | N125: AC=5 (Medium) +1: seven-role higher-officials chain
A126: 118 | B126: US-AUG-11 | C126: Sprint 19 User Stories (Aug 2026) | D126: O&M Billing — Data Integrity - Census Population / village denominator fix | E126: In Progress | F126: Aug 2026 | G126: Yes | H126: O&M Estimation | I126: O&M Billing - Data Integrity & Adjustments | J126: 4 | L126: Medium | M126: =IF(L126="Low",1,IF(L126="Medium",3,IF(L126="High",5,0))) -> 3 | N126: AC=4 (Medium): denominator rule and sequence-date enforcement
A127: 119 | B127: US-AUG-12 | C127: Sprint 19 User Stories (Aug 2026) | D127: O&M Billing — UI/Workflow - 'Pending Bills for Review' rename and scheme filter | E127: In Progress | F127: Aug 2026 | G127: Yes | H127: O&M Estimation | I127: O&M Billing - Data Integrity & Adjustments | J127: 5 | L127: Low | M127: =IF(L127="Low",1,IF(L127="Medium",3,IF(L127="High",5,0))) -> 1 | N127: AC=5 (Medium) -1: rename, filter option, date columns (UI/labels)
... A129: 121 | B129: US-AUG-14 | C129: Sprint 19 User Stories (Aug 2026) | D129: O&M Billing — Complaint Handling - Complaint category coding and extended deductions | E129: In Progress | F129: Aug 2026 | G129: Yes | H129: O&M Estimation | I129: O&M Billing - Data Integrity & Adjustments | J129: 4 | L129: Medium | M129: =IF(L129="Low",1,IF(L129="Medium",3,IF(L129="High",5,0))) -> 3 | N129: AC=4 (Medium): five complaint categories with reason and document
A130: 122 | B130: US-AUG-15 | C130: Sprint 19 User Stories (Aug 2026) | D130: O&M Billing — GST - GST Number on Bill and Abstract | E130: Open | F130: Aug 2026 | G130: No | J130: 4 | M130: =IF(L130="Low",1,IF(L130="Medium",3,IF(L130="High",5,0))) -> 0 | N130: Excluded: Duplicate of US-OM-C5-017 (GST Number, same CR OMB-MAY-2026-003)
A131: 123 | B131: US-AUG-16 | C131: Sprint 19 User Stories (Aug 2026) | D131: O&M Billing — LGD Integration - LGD Code integration (LG Directory → MPSQC) | E131: In Progress | F131: Aug 2026 | G131: No | J131: 4 | M131: =IF(L131="Low",1,IF(L131="Medium",3,IF(L131="High",5,0))) -> 0 | N131: Excluded: Duplicate of US-OM-C5-014 (LGD code integration)
A132: 124 | B132: US-AUG-17 | C132: Sprint 19 User Stories (Aug 2026) | D132: O&M Billing — Contractor Discrepancy - Contractor discrepancy time-window on Dhara data | E132: In Progress | F132: Aug 2026 | G132: No | J132: 4 | M132: =IF(L132="Low",1,IF(L132="Medium",3,IF(L132="High",5,0))) -> 0 | N132: Excluded: Duplicate of US-OM-C5-008 (Contractor dispute window on Dhara data)
A133: 125 | B133: US-AUG-18 | C133: Sprint 19 User Stories (Aug 2026) | D133: O&M Billing — Aakalan - Aakalan Addition/Deduction feature (TL SQC / GM PIU) | E133: Done | F133: Aug 2026 | G133: Yes | H133: O&M Estimation | I133: O&M Billing - Data Integrity & Adjustments | J133: 5 | L133: Medium | M133: =IF(L133="Low",1,IF(L133="Medium",3,IF(L133="High",5,0))) -> 3 | N133: AC=5 (Medium): role-restricted adjustment with audit in consolidated abstract
A134: 126 | B134: US-AUG-19 | C134: Sprint 19 User Stories (Aug 2026) | D134: SVS Water Supply Dashboard - SVS Water Supply Status Dashboard V2 — KPI cards and colour coding | E134: In Progress | F134: Aug 2026 | G134: Yes | H134: SVS Estimation | I134: SVS - Dashboard V2 & Drill-down | J134: 5 | L134: High | M134: =IF(L134="Low",1,IF(L134="Medium",3,IF(L134="High",5,0))) -> 5 | N134: AC=5 (Medium) +1: dashboard with KPI cards, colour rules and workflow
A135: 127 | B135: US-AUG-20 | C135: Sprint 19 User Stories (Aug 2026) | D135: SVS Water Supply Dashboard - SVS dashboard drill-down — Gram Sachiv and CEO/CO Block | E135: In Progress | F135: Aug 2026 | G135: Yes | H135: SVS Estimation | I135: SVS - Dashboard V2 & Drill-down | J135: 4 | L135: High | M135: =IF(L135="Low",1,IF(L135="Medium",3,IF(L135="High",5,0))) -> 5 | N135: AC=4 (Medium) +1: role-specific drill-down with approve/reject
A136: 128 | B136: US-AUG-21 | C136: Sprint 19 User Stories (Aug 2026) | D136: SVS / MVS Master - SVS master wireframe and MVS Master (600+ entries) | E136: In Progress | F136: Aug 2026 | G136: Yes | H136: SVS Estimation | I136: SVS / MVS - Master | J136: 4 | L136: Medium | M136: =IF(L136="Low",1,IF(L136="Medium",3,IF(L136="High",5,0))) -> 3 | N136: AC=4 (Medium): master wireframe and 600+ entry master mirroring Vistrit
A137: 129 | B137: US-AUG-22 | C137: Sprint 19 User Stories (Aug 2026) | D137: SVS / Dhara Meter Logic - FE/Dhara Meter Functional logic and sequential approval | E137: In Progress | F137: Aug 2026 | G137: Yes | H137: Dhara Estimation | I137: Dhara - Meter Logic & Sequential Approval | J137: 4 | L137: Medium | M137: =IF(L137="Low",1,IF(L137="Medium",3,IF(L137="High",5,0))) -> 3 | N137: AC=4 (Medium): meter functional/absent logic and sequential approval
A138: 130 | B138: US-AUG-23 | C138: Sprint 19 User Stories (Aug 2026) | D138: Nirmal / SVS PHE - Nirmal/SVS PHE integration logic and status labelling | E138: In Progress | F138: Aug 2026 | G138: Yes | H138: Nirmal Estimation | I138: Nirmal / SVS PHE - Water Testing | J138: 5 | L138: Medium | M138: =IF(L138="Low",1,IF(L138="Medium",3,IF(L138="High",5,0))) -> 3 | N138: AC=5 (Medium): status labelling, colour coding, drill-down, approval lock
A139: 131 | B139: US-AUG-24 | C139: Sprint 19 User Stories (Aug 2026) | D139: Nirmal / SVS PHE - Nirmal/SVS PHE water-testing entry form | E139: In Progress | F139: Aug 2026 | G139: Yes | H139: Nirmal Estimation | I139: Nirmal / SVS PHE - Water Testing | J139: 6 | L139: High | M139: =IF(L139="Low",1,IF(L139="Medium",3,IF(L139="High",5,0))) -> 5 | N139: AC=6 (High): multi-field water-testing form with pass/fail logic and photos
A140: 132 | B140: US-AUG-25 | C140: Sprint 19 User Stories (Aug 2026) | D140: Material Testing - Material Testing 2nd-loop re-inspection — production deployment | E140: In Progress | F140: Aug 2026 | G140: No | J140: 5 | M140: =IF(L140="Low",1,IF(L140="Medium",3,IF(L140="High",5,0))) -> 0 | N140: Excluded: Production deployment of scope already sized in US-MAT-C5-001/002/003
A141: 133 | B141: US-AUG-26 | C141: Sprint 19 User Stories (Aug 2026) | D141: Sahbhagita - Sahbhagita Abstract of RA Bill — production release | E141: In Progress | F141: Aug 2026 | G141: Yes | H141: Sahbhagita Estimation | I141: Sahbhagita - Abstract of RA Bill Release | J141: 5 | L141: Low | M141: =IF(L141="Low",1,IF(L141="Medium",3,IF(L141="High",5,0))) -> 1 | N141: AC=5 (Medium) -1: UAT defect fixes and release of work sized in Jun (SAH-C5-002/006)
A142: 134 | B142: US-AUG-27 | C142: Sprint 19 User Stories (Aug 2026) | D142: FHTC / Parinam - Parinam Dashboard tab on HSC Survey screen | E142: Done | F142: Aug 2026 | G142: Yes | H142: FHTC Estimation | I142: FHTC Parinam - Dashboard | J142: 4 | L142: Low | M142: =IF(L142="Low",1,IF(L142="Medium",3,IF(L142="High",5,0))) -> 1 | N142: AC=4 (Medium) -1: display-only dashboard tab
A143: 135 | B143: US-AUG-28 | C143: Sprint 19 User Stories (Aug 2026) | D143: Mobile App - Mobile app UI/functional bug fixes | E143: Done | F143: Aug 2026 | G143: Yes | H143: Other Modules Estimation | I143: Mobile App - Fixes & Stability | J143: 6 | L143: Medium | M143: =IF(L143="Low",1,IF(L143="Medium",3,IF(L143="High",5,0))) -> 3 | N143: AC=6 (High) -1: mobile navigation and duplicate-control fixes
A144: 136 | B144: US-AUG-29 | C144: Sprint 19 User Stories (Aug 2026) | D144: CMMI L5 - Cycle 4 BRTM and Release Note closure | E144: In Progress | F144: Aug 2026 | G144: Yes | H144: CMMI Doc Estimation | I144: CMMI Doc - Cycle 4 Closure | J144: 6 | L144: High | M144: =IF(L144="Low",1,IF(L144="Medium",3,IF(L144="High",5,0))) -> 5 | N144: AC=6 (High): BRTM, release note, code review, SVN, Minitab
A145: 137 | B145: US-AUG-30 | C145: Sprint 19 User Stories (Aug 2026) | D145: Master Data - Master Data Lock scope finalisation | E145: Open | F145: Aug 2026 | G145: No | J145: 4 | M145: =IF(L145="Low",1,IF(L145="Medium",3,IF(L145="High",5,0))) -> 0 | N145: Excluded: Duplicate of US-MSTR-C5-001 (Master lock, CR MSTR-JUN-2026-006)
A146: 138 | B146: US-AUG-31 | C146: Sprint 19 User Stories (Aug 2026) | D146: BISAG / Delhi Data Integration - Asset & Pipeline API and Annexure-C data sharing | E146: In Progress | F146: Aug 2026 | G146: Yes | H146: BISAC-BISAG Estimation | I146: BISAG - Delhi Data Integration | J146: 5 | L146: High | M146: =IF(L146="Low",1,IF(L146="Medium",3,IF(L146="High",5,0))) -> 5 | N146: AC=5 (Medium) +1: external BISAG API and Annexure-C data sharing
A147: 139 | B147: US-AUG-32 | C147: Sprint 19 User Stories (Aug 2026) | D147: BISAG / Delhi Data Integration - Scheme mapping and progress-reporting fix | E147: In Progress | F147: Aug 2026 | G147: Yes | H147: BISAC-BISAG Estimation | I147: BISAG - Delhi Data Integration | J147: 5 | L147: Medium | M147: =IF(L147="Low",1,IF(L147="Medium",3,IF(L147="High",5,0))) -> 3 | N147: AC=5 (Medium): integration (+1) offset by fix scope (-1)
A148: 140 | B148: US-AUG-33 | C148: Sprint 19 User Stories (Aug 2026) | D148: Contractor Billing Acceleration - Hands-on training for non-submitting agencies | E148: Done | F148: Aug 2026 | G148: No | J148: 5 | M148: =IF(L148="Low",1,IF(L148="Medium",3,IF(L148="High",5,0))) -> 0 | N148: Excluded: Hands-on training for agencies - operational activity, not development scope
A149: 141 | B149: US-AUG-34 | C149: Sprint 19 User Stories (Aug 2026) | D149: Dhara & Nirmal Panchayat Monitoring - Panchayat-level dashboard and MVS-to-local-body handover | E149: In Progress | F149: Aug 2026 | G149: Yes | H149: Dhara Estimation | I149: Dhara & Nirmal - Panchayat Monitoring | J149: 6 | L149: High | M149: =IF(L149="Low",1,IF(L149="Medium",3,IF(L149="High",5,0))) -> 5 | N149: AC=6 (High): panchayat dashboards for two modules plus 5-step handover
A150: 142 | B150: US-AUG-35 | C150: Sprint 19 User Stories (Aug 2026) | D150: RFI / Anusharavan (SVS-GP) - Simplified RFI system and GP–FE review workflow | E150: Not Started | F150: Aug 2026 | G150: Yes | H150: SVS Anusharavan GP Estimation | I150: SVS Anusharavan GP - Mobile & RFI Workflow | J150: 9 | L150: High | M150: =IF(L150="Low",1,IF(L150="Medium",3,IF(L150="High",5,0))) -> 5 | N150: AC=9 (High): simplified RFI with geotag, classification and review workflow
A151: 143 | B151: US-AUG-36 | C151: Sprint 19 User Stories (Aug 2026) | D151: Admin / ID Management - PIU district-wise restructuring and TL-ID/PIU-ID linking | E151: Not Started | F151: Aug 2026 | G151: Yes | H151: Other Modules Estimation | I151: Admin / ID Management | J151: 6 | L151: High | M151: =IF(L151="Low",1,IF(L151="Medium",3,IF(L151="High",5,0))) -> 5 | N151: AC=6 (High): PIU restructuring, ID linking, agency re-mapping protocol
A152: 144 | B152: US-AUG-37 | C152: Sprint 19 User Stories (Aug 2026) | D152: Jal Samadhan - Complaint Queries module | E152: Not Started | F152: Aug 2026 | G152: Yes | H152: Other Modules Estimation | I152: Jal Samadhan | J152: 4 | L152: Medium | M152: =IF(L152="Low",1,IF(L152="Medium",3,IF(L152="High",5,0))) -> 3 | N152: AC=4 (Medium): complaint queries page with SLA escalation
A153: 145 | B153: US-SEP-01 | C153: Sprint 20 User Stories (Sep 2026) | D153: O&M Billing / Aaklan - O&M Billing workflow confirmed stable in production | E153: Done | F153: Sep 2026 | G153: No | J153: 4 | M153: =IF(L153="Low",1,IF(L153="Medium",3,IF(L153="High",5,0))) -> 0 | N153: Excluded: Production confirmation of workflow scope already sized (US-AUG-01/07/08/12/18)
A154: 146 | B154: US-SEP-02 | C154: Sprint 20 User Stories (Sep 2026) | D154: O&M Billing / Aaklan - Withheld Addition/Deduction amounts shown at End-of-Month | E154: In Progress | F154: Sep 2026 | G154: Yes | H154: O&M Estimation | I154: O&M Billing / Aaklan - Controls & Tracking | J154: 4 | L154: Medium | M154: =IF(L154="Low",1,IF(L154="Medium",3,IF(L154="High",5,0))) -> 3 | N154: AC=4 (Medium)
A155: 147 | B155: US-SEP-03 | C155: Sprint 20 User Stories (Sep 2026) | D155: O&M Billing / Aaklan - Fix: bill remains editable after Contractor submission | E155: Done | F155: Sep 2026 | G155: Yes | H155: O&M Estimation | I155: O&M Billing / Aaklan - Controls & Tracking | J155: 3 | L155: Low | M155: =IF(L155="Low",1,IF(L155="Medium",3,IF(L155="High",5,0))) -> 1 | N155: AC=3 (Low): client-side lock fix
A156: 148 | B156: US-SEP-04 | C156: Sprint 20 User Stories (Sep 2026) | D156: O&M Billing / Aaklan - TRP gate controlling O&M Phase availability | E156: In Progress | F156: Sep 2026 | G156: Yes | H156: O&M Estimation | I156: O&M Billing / Aaklan - Controls & Tracking | J156: 3 | L156: Low | M156: =IF(L156="Low",1,IF(L156="Medium",3,IF(L156="High",5,0))) -> 1 | N156: AC=3 (Low): phase-availability gate
A157: 149 | B157: US-SEP-05 | C157: Sprint 20 User Stories (Sep 2026) | D157: O&M Billing / Aaklan - Scheme-based SQC/TL list cleanup | E157: In Progress | F157: Sep 2026 | G157: Yes | H157: O&M Estimation | I157: O&M Billing / Aaklan - Controls & Tracking | J157: 4 | L157: Low | M157: =IF(L157="Low",1,IF(L157="Medium",3,IF(L157="High",5,0))) -> 1 | N157: AC=4 (Medium) -1: list cleanup
A158: 150 | B158: US-SEP-06 | C158: Sprint 20 User Stories (Sep 2026) | D158: O&M Billing / Aaklan - WSDCP / TRP / O&M Phase tabs with staged Abstract pages | E158: In Progress | F158: Sep 2026 | G158: Yes | H158: O&M Estimation | I158: O&M Billing / Aaklan - Controls & Tracking | J158: 3 | L158: Medium | M158: =IF(L158="Low",1,IF(L158="Medium",3,IF(L158="High",5,0))) -> 3 | N158: AC=3 (Low) +1: three phase tabs with staged abstract pages
A159: 151 | B159: US-SEP-07 | C159: Sprint 20 User Stories (Sep 2026) | D159: O&M Billing / Aaklan - Full audit trail on Contractor Bill edits | E159: Open | F159: Sep 2026 | G159: Yes | H159: O&M Estimation | I159: O&M Billing / Aaklan - Controls & Tracking | J159: 4 | L159: Medium | M159: =IF(L159="Low",1,IF(L159="Medium",3,IF(L159="High",5,0))) -> 3 | N159: AC=4 (Medium): audit trail on contractor bill edits
A160: 152 | B160: US-SEP-08 | C160: Sprint 20 User Stories (Sep 2026) | D160: O&M Billing / Aaklan - PMC / Deputy O&M role-scoped scheme visibility | E160: Open | F160: Sep 2026 | G160: Yes | H160: O&M Estimation | I160: O&M Billing / Aaklan - Controls & Tracking | J160: 4 | L160: Medium | M160: =IF(L160="Low",1,IF(L160="Medium",3,IF(L160="High",5,0))) -> 3 | N160: AC=4 (Medium): role-scoped visibility
A161: 153 | B161: US-SEP-09 | C161: Sprint 20 User Stories (Sep 2026) | D161: O&M Billing / Aaklan - Gross Payable Bill — minimum value validation | E161: Open | F161: Sep 2026 | G161: Yes | H161: O&M Estimation | I161: O&M Billing / Aaklan - Controls & Tracking | J161: 3 | L161: Low | M161: =IF(L161="Low",1,IF(L161="Medium",3,IF(L161="High",5,0))) -> 1 | N161: AC=3 (Low): minimum-value validation
A162: 154 | B162: US-SEP-10 | C162: Sprint 20 User Stories (Sep 2026) | D162: O&M Billing / Aaklan - Census Population verification before Generate Bill | E162: Done | F162: Sep 2026 | G162: Yes | H162: O&M Estimation | I162: O&M Billing / Aaklan - Controls & Tracking | J162: 3 | L162: Low | M162: =IF(L162="Low",1,IF(L162="Medium",3,IF(L162="High",5,0))) -> 1 | N162: AC=3 (Low): pre-generation census check
A163: 155 | B163: US-SEP-11 | C163: Sprint 20 User Stories (Sep 2026) | D163: O&M Billing / Aaklan - User Management — PIU-wise ID search with Tenure and Agency columns | E163: In Progress | F163: Sep 2026 | G163: Yes | H163: O&M Estimation | I163: O&M Billing / Aaklan - Controls & Tracking | J163: 4 | L163: Medium | M163: =IF(L163="Low",1,IF(L163="Medium",3,IF(L163="High",5,0))) -> 3 | N163: AC=4 (Medium): PIU-wise ID search with tenure/agency columns
A164: 156 | B164: US-SEP-12 | C164: Sprint 20 User Stories (Sep 2026) | D164: O&M Billing / Aaklan - TL ID conflict resolution (Bhopal / Sehore) | E164: Open | F164: Sep 2026 | G164: Yes | H164: O&M Estimation | I164: O&M Billing / Aaklan - Controls & Tracking | J164: 3 | L164: Low | M164: =IF(L164="Low",1,IF(L164="Medium",3,IF(L164="High",5,0))) -> 1 | N164: AC=3 (Low): TL ID conflict resolution
A165: 157 | B165: US-SEP-13 | C165: Sprint 20 User Stories (Sep 2026) | D165: O&M Billing / Aaklan - Save-as-Draft confirmation popup on Bulk bill actions | E165: Open | F165: Sep 2026 | G165: Yes | H165: O&M Estimation | I165: O&M Billing / Aaklan - Controls & Tracking | J165: 3 | L165: Low | M165: =IF(L165="Low",1,IF(L165="Medium",3,IF(L165="High",5,0))) -> 1 | N165: AC=3 (Low) -1: confirmation popup
... A178: 170 | B178: US-SEP-26 | C178: Sprint 20 User Stories (Sep 2026) | D178: Parinam - FE dashboard, FE-login reports, and multi-survey support confirmed stable | E178: Done | F178: Sep 2026 | G178: Yes | H178: FHTC Estimation | I178: FHTC Parinam - Dashboard | J178: 4 | L178: Low | M178: =IF(L178="Low",1,IF(L178="Medium",3,IF(L178="High",5,0))) -> 1 | N178: AC=4 (Medium) -1: only the new FE dashboard/FE-login reports sized; FE name and multi-survey already sized in FHTC-C5-002/005
...
